{
  "id": "algorand",
  "symbol": "algo",
  "name": "Algorand",
  "web_slug": "algorand",
  "asset_platform_id": null,
  "platforms": {
    "": ""
  },
  "detail_platforms": {
    "": {
      "decimal_place": null,
      "contract_address": ""
    }
  },
  "block_time_in_minutes": 0,
  "hashing_algorithm": null,
  "categories": [
    "Smart Contract Platform",
    "Layer 1 (L1)",
    "Algorand Ecosystem",
    "Real World Assets (RWA)",
    "Alleged SEC Securities",
    "DWF Labs Portfolio",
    "Multicoin Capital Portfolio",
    "Proof of Stake (PoS)",
    "GMCI Layer 1 Index",
    "GMCI Index",
    "Made in USA",
    "Coinbase 50 Index",
    "CoinList Launchpad"
  ],
  "preview_listing": false,
  "public_notice": null,
  "additional_notices": [],
  "description": {
    "en": "Algorand is a scalable, secure, and decentralized digital currency and smart contract platform. Its protocol uses a variation of Proof-of-Stake (PoS) called Pure PoS (PPoS) to secure the network and reach consensus on block production. Developers can build decentralized applications (dApps) using familiar programming languages, including Python, which Algorand supports natively. Its infrastructure enables various use cases, including payment systems, digital identity solutions, supply-chain tracking, and financial services. The protocol's architecture allows for tokenization of assets and the development of smart contracts, while its technical specifications support both retail users seeking basic transaction capabilities and enterprises requiring more, complex, blockchain solutions."
  },
  "links": {
    "homepage": [
      "https://algorand.foundation/",
      "https://www.algorand.com/",
      "https://www.algorand.com/resources"
    ],
    "whitepaper": "https://www.algorand.com/technology/white-papers",
    "blockchain_site": [
      "https://allo.info/",
      "https://explorer.perawallet.app/",
      "https://explorer.bitquery.io/algorand",
      "https://lora.algokit.io/mainnet",
      "https://algo.surf/",
      "https://algogazer.app/"
    ],
    "official_forum_url": [],
    "chat_url": [
      "https://discord.gg/QBYp7Y2"
    ],
    "announcement_url": [
      "https://medium.com/algorand",
      "https://forum.algorand.org/"
    ],
    "snapshot_url": null,
    "twitter_screen_name": "algorand",
    "facebook_username": "",
    "bitcointalk_thread_identifier": null,
    "telegram_channel_identifier": "algorand",
    "subreddit_url": "https://www.reddit.com/r/AlgorandOfficial/",
    "repos_url": {
      "github": [
        "https://github.com/algorand/go-algorand",
        "https://github.com/algorand/java-algorand-sdk",
        "https://github.com/algorand/js-algorand-sdk",
        "https://github.com/algorand/go-algorand-sdk"
      ],
      "bitbucket": []
    }
  },
  "image": {
    "thumb": "https://coin-images.coingecko.com/coins/images/4380/thumb/download.png?1696504978",
    "small": "https://coin-images.coingecko.com/coins/images/4380/small/download.png?1696504978",
    "large": "https://coin-images.coingecko.com/coins/images/4380/large/download.png?1696504978"
  },
  "country_origin": "",
  "genesis_date": null,
  "sentiment_votes_up_percentage": 90.91,
  "sentiment_votes_down_percentage": 9.09,
  "ico_data": {
    "ico_start_date": "2019-06-19T00:00:00.000Z",
    "ico_end_date": null,
    "short_desc": "Powered by consensus.",
    "description": "",
    "links": {},
    "softcap_currency": "",
    "hardcap_currency": "",
    "total_raised_currency": "USD",
    "softcap_amount": null,
    "hardcap_amount": null,
    "total_raised": "60402219.75",
    "quote_pre_sale_currency": "",
    "base_pre_sale_amount": null,
    "quote_pre_sale_amount": null,
    "quote_public_sale_currency": "USD",
    "base_public_sale_amount": 1,
    "quote_public_sale_amount": 2.4,
    "accepting_currencies": "",
    "country_origin": "",
    "pre_sale_start_date": null,
    "pre_sale_end_date": null,
    "whitelist_url": "",
    "whitelist_start_date": null,
    "whitelist_end_date": null,
    "bounty_detail_url": "",
    "amount_for_sale": null,
    "kyc_required": true,
    "whitelist_available": null,
    "pre_sale_available": null,
    "pre_sale_ended": false
  },
  "watchlist_portfolio_users": 288327,
  "market_cap_rank": 78,
  "market_cap_rank_with_rehypothecated": 103,
  "market_data": {
    "current_price": {
      "aed": 0.337301,
      "ars": 128.11,
      "aud": 0.131414,
      "bch": 0.00019628,
      "bdt": 11.27,
      "bhd": 0.03490582,
      "bmd": 0.091845,
      "bnb": 0.00013848,
      "brl": 0.489617,
      "btc": 0.00000128,
      "cad": 0.126843,
      "chf": 0.073104,
      "clp": 84.26,
      "cny": 0.633419,
      "czk": 1.97,
      "dkk": 0.601135,
      "dot": 0.06419105,
      "eos": 1.127208,
      "eth": 0.00004333,
      "eur": 0.08012,
      "gbp": 0.069385,
      "gel": 0.250737,
      "hkd": 0.719188,
      "huf": 31.34,
      "idr": 1557.7,
      "ils": 0.288812,
      "inr": 8.5,
      "jpy": 14.67,
      "krw": 138.02,
      "kwd": 0.02820333,
      "lkr": 28.58,
      "ltc": 0.00165706,
      "mmk": 192.86,
      "mxn": 1.65,
      "myr": 0.361732,
      "ngn": 127.28,
      "nok": 0.895143,
      "nzd": 0.158984,
      "php": 5.47,
      "pkr": 25.64,
      "pln": 0.341435,
      "rub": 7.34,
      "sar": 0.344689,
      "sek": 0.870756,
      "sgd": 0.117699,
      "sol": 0.00103694,
      "thb": 2.96,
      "try": 4.06,
      "twd": 2.95,
      "uah": 4.05,
      "usd": 0.091845,
      "vef": 0.00919645,
      "vnd": 2415.07,
      "xag": 0.00113939,
      "xau": 0.0000183,
      "xdr": 0.065327,
      "xlm": 0.54675823,
      "xrp": 0.06485517,
      "yfi": 0.00003555,
      "zar": 1.55,
      "bits": 1.28,
      "link": 0.00989471,
      "sats": 127.84
    },
    "total_value_locked": null,
    "mcap_to_tvl_ratio": null,
    "fdv_to_tvl_ratio": null,
    "roi": {
      "times": -0.9617312100695259,
      "currency": "usd",
      "percentage": -96.17312100695258
    },
    "ath": {
      "aed": 13.08,
      "ars": 609.42,
      "aud": 5.14,
      "bch": 0.00869058,
      "bdt": 300.86,
      "bhd": 1.34,
      "bmd": 3.56,
      "bnb": 0.09801689,
      "brl": 14.71,
      "btc": 0.0003803,
      "cad": 4.7,
      "chf": 3.5,
      "clp": 2436.19,
      "cny": 24.4,
      "czk": 80.73,
      "dkk": 23.54,
      "dot": 0.21708002,
      "eos": 1.22538,
      "eth": 0.01321325,
      "eur": 3.15,
      "gbp": 2.8,
      "gel": 1.71,
      "hkd": 27.84,
      "huf": 1019,
      "idr": 50402,
      "ils": 12.76,
      "inr": 247.29,
      "jpy": 382.89,
      "krw": 4127.02,
      "kwd": 1.082,
      "lkr": 629.08,
      "ltc": 0.02631169,
      "mmk": 5420.24,
      "mxn": 67.67,
      "myr": 14.75,
      "ngn": 1142.05,
      "nok": 30.52,
      "nzd": 5.41,
      "php": 183.1,
      "pkr": 559.1,
      "pln": 13.41,
      "rub": 224.36,
      "sar": 13.35,
      "sek": 33.53,
      "sgd": 51340,
      "sol": 0.0018665,
      "thb": 109.91,
      "try": 28.9,
      "twd": 110.33,
      "uah": 93.83,
      "usd": 3.56,
      "vef": 884903,
      "vnd": 83042,
      "xag": 0.231409,
      "xau": 0.00257361,
      "xdr": 2.56,
      "xlm": 29.187366,
      "xrp": 8.329044,
      "yfi": 0.00044786,
      "zar": 50.97,
      "bits": 313.42,
      "link": 1.862856,
      "sats": 31342
    },
    "ath_change_percentage": {
      "aed": -97.41067,
      "ars": -78.89118,
      "aud": -97.4345,
      "bch": -97.72681,
      "bdt": -96.23879,
      "bhd": -97.38935,
      "bmd": -97.41021,
      "bnb": -99.85816,
      "brl": -96.65844,
      "btc": -99.66248,
      "cad": -97.28984,
      "chf": -97.89984,
      "clp": -96.52689,
      "cny": -97.39335,
      "czk": -97.5517,
      "dkk": -97.43536,
      "dot": -70.29963,
      "eos": -7.25126,
      "eth": -99.67049,
      "eur": -97.44801,
      "gbp": -97.51416,
      "gel": -85.30394,
      "hkd": -97.40569,
      "huf": -96.91181,
      "idr": -96.89662,
      "ils": -97.72629,
      "inr": -96.54712,
      "jpy": -96.15223,
      "krw": -96.6418,
      "kwd": -97.38143,
      "lkr": -95.43764,
      "ltc": -93.67229,
      "mmk": -96.42713,
      "mxn": -97.55366,
      "myr": -97.5379,
      "ngn": -88.80853,
      "nok": -97.05478,
      "nzd": -97.05076,
      "php": -96.99861,
      "pkr": -95.39445,
      "pln": -97.44302,
      "rub": -96.71532,
      "sar": -97.40818,
      "sek": -97.39231,
      "sgd": -99.99977,
      "sol": -44.2076,
      "thb": -97.29399,
      "try": -85.90624,
      "twd": -97.3121,
      "uah": -95.66564,
      "usd": -97.41021,
      "vef": -100,
      "vnd": -97.07968,
      "xag": -99.50559,
      "xau": -99.28616,
      "xdr": -97.43862,
      "xlm": -98.12166,
      "xrp": -99.2181,
      "yfi": -92.02903,
      "zar": -96.94494,
      "bits": -99.59045,
      "link": -99.46614,
      "sats": -99.59045
    },
    "ath_date": {
      "aed": "2019-06-20T14:51:19.480Z",
      "ars": "2024-12-03T13:16:13.713Z",
      "aud": "2019-06-20T14:51:19.480Z",
      "bch": "2019-06-20T14:51:19.480Z",
      "bdt": "2019-06-20T14:51:19.480Z",
      "bhd": "2019-06-20T14:51:19.480Z",
      "bmd": "2019-06-20T14:51:19.480Z",
      "bnb": "2019-06-20T14:51:19.480Z",
      "brl": "2021-11-18T04:33:59.145Z",
      "btc": "2019-06-20T14:51:19.480Z",
      "cad": "2019-06-20T14:51:19.480Z",
      "chf": "2019-06-20T14:51:19.480Z",
      "clp": "2019-06-20T14:51:19.480Z",
      "cny": "2019-06-20T14:51:19.480Z",
      "czk": "2019-06-20T14:51:19.480Z",
      "dkk": "2019-06-20T14:51:19.480Z",
      "dot": "2020-08-21T00:00:00.000Z",
      "eos": "2026-02-09T06:40:11.039Z",
      "eth": "2019-06-20T14:51:19.480Z",
      "eur": "2019-06-20T14:51:19.480Z",
      "gbp": "2019-06-20T14:51:19.480Z",
      "gel": "2024-12-03T13:16:13.713Z",
      "hkd": "2019-06-20T14:51:19.480Z",
      "huf": "2019-06-20T14:51:19.480Z",
      "idr": "2019-06-20T14:51:19.480Z",
      "ils": "2019-06-20T14:51:19.480Z",
      "inr": "2019-06-20T14:51:19.480Z",
      "jpy": "2019-06-20T14:51:19.480Z",
      "krw": "2019-06-20T14:51:19.480Z",
      "kwd": "2019-06-20T14:51:19.480Z",
      "lkr": "2019-06-20T14:51:19.480Z",
      "ltc": "2019-06-20T14:51:19.480Z",
      "mmk": "2019-06-20T14:51:19.480Z",
      "mxn": "2019-06-20T14:51:19.480Z",
      "myr": "2019-06-20T14:51:19.480Z",
      "ngn": "2019-06-22T00:00:00.000Z",
      "nok": "2019-06-20T14:51:19.480Z",
      "nzd": "2019-06-20T14:51:19.480Z",
      "php": "2019-06-20T14:51:19.480Z",
      "pkr": "2019-06-20T14:51:19.480Z",
      "pln": "2019-06-20T14:51:19.480Z",
      "rub": "2019-06-20T14:51:19.480Z",
      "sar": "2019-06-20T14:51:19.480Z",
      "sek": "2019-06-20T14:51:19.480Z",
      "sgd": "2022-05-08T11:59:52.733Z",
      "sol": "2025-07-18T01:01:26.242Z",
      "thb": "2019-06-20T14:51:19.480Z",
      "try": "2021-11-18T04:33:59.145Z",
      "twd": "2019-06-20T14:51:19.480Z",
      "uah": "2019-06-20T14:51:19.480Z",
      "usd": "2019-06-20T14:51:19.480Z",
      "vef": "2019-06-20T14:51:19.480Z",
      "vnd": "2019-06-20T14:51:19.480Z",
      "xag": "2019-06-20T14:51:19.480Z",
      "xau": "2019-06-20T14:51:19.480Z",
      "xdr": "2019-06-20T14:51:19.480Z",
      "xlm": "2019-06-20T14:51:19.480Z",
      "xrp": "2019-06-20T14:51:19.480Z",
      "yfi": "2020-07-19T00:00:00.000Z",
      "zar": "2019-06-20T14:51:19.480Z",
      "bits": "2019-06-22T00:00:00.000Z",
      "link": "2019-06-22T00:00:00.000Z",
      "sats": "2019-06-22T00:00:00.000Z"
    },
    "atl": {
      "aed": 0.299482,
      "ars": 6.6,
      "aud": 0.115219,
      "bch": 0.00015096,
      "bdt": 8.99,
      "bhd": 0.03065202,
      "bmd": 0.081545,
      "bnb": 0.00012614,
      "brl": 0.420609,
      "btc": 0.0000012,
      "cad": 0.110745,
      "chf": 0.063084,
      "clp": 71.63,
      "cny": 0.562305,
      "czk": 1.68,
      "dkk": 0.51853,
      "dot": 0.02004984,
      "eos": 0.05534586,
      "eth": 0.00003647,
      "eur": 0.069383,
      "gbp": 0.06081,
      "gel": 0.218914,
      "hkd": 0.637799,
      "huf": 26.14,
      "idr": 1343.06,
      "ils": 0.252232,
      "inr": 7.26,
      "jpy": 11.07,
      "krw": 116.08,
      "kwd": 0.02505681,
      "lkr": 19.37,
      "ltc": 0.00103822,
      "mmk": 147.09,
      "mxn": 1.41,
      "myr": 0.319048,
      "ngn": 45.46,
      "nok": 0.77966,
      "nzd": 0.13673,
      "php": 4.73,
      "pkr": 16.86,
      "pln": 0.293033,
      "rub": 6.32,
      "sar": 0.306643,
      "sek": 0.740444,
      "sgd": 0.103685,
      "sol": 0.0007391,
      "thb": 2.53,
      "try": 0.665626,
      "twd": 2.57,
      "uah": 2.74,
      "usd": 0.081545,
      "vef": 0.0081651,
      "vnd": 2105.97,
      "xag": 0.00088934,
      "xau": 0.00001553,
      "xdr": 0.056591,
      "xlm": 0.48647439,
      "xrp": 0.05762154,
      "yfi": 0.00000878,
      "zar": 1.31,
      "bits": 1.2,
      "link": 0.00795659,
      "sats": 120.24
    },
    "atl_change_percentage": {
      "aed": 13.09593,
      "ars": 1847.81322,
      "aud": 14.529,
      "bch": 30.86065,
      "bdt": 25.89148,
      "bhd": 14.35068,
      "bmd": 13.099,
      "bnb": 10.21924,
      "brl": 16.89011,
      "btc": 6.75215,
      "cad": 15.012,
      "chf": 16.36474,
      "clp": 18.1206,
      "cny": 13.11481,
      "czk": 17.47904,
      "dkk": 16.41218,
      "dot": 221.56644,
      "eos": 1953.49443,
      "eth": 19.38112,
      "eur": 15.95377,
      "gbp": 14.57537,
      "gel": 15.01274,
      "hkd": 13.22936,
      "huf": 20.40003,
      "idr": 16.46285,
      "ils": 14.97811,
      "inr": 17.69187,
      "jpy": 33.11792,
      "krw": 19.38973,
      "kwd": 13.02502,
      "lkr": 48.15265,
      "ltc": 60.36403,
      "mmk": 31.66321,
      "mxn": 17.15142,
      "myr": 13.84939,
      "ngn": 181.13272,
      "nok": 15.28872,
      "nzd": 16.75893,
      "php": 16.08218,
      "pkr": 52.70883,
      "pln": 17.00147,
      "rub": 16.60585,
      "sar": 12.87394,
      "sek": 18.08751,
      "sgd": 13.98823,
      "sol": 40.89752,
      "thb": 17.3292,
      "try": 511.93346,
      "twd": 15.22813,
      "uah": 48.46044,
      "usd": 13.099,
      "vef": 13.099,
      "vnd": 15.15374,
      "xag": 28.64802,
      "xau": 18.26776,
      "xdr": 15.91765,
      "xlm": 12.69603,
      "xrp": 13.02197,
      "yfi": 306.61371,
      "zar": 19.22476,
      "bits": 6.75215,
      "link": 24.99153,
      "sats": 6.75215
    },
    "atl_date": {
      "aed": "2026-03-08T22:30:13.394Z",
      "ars": "2020-03-13T02:20:48.438Z",
      "aud": "2026-02-28T10:15:10.351Z",
      "bch": "2026-02-23T01:16:29.739Z",
      "bdt": "2020-03-13T02:20:48.438Z",
      "bhd": "2026-03-08T22:30:13.394Z",
      "bmd": "2026-03-08T22:30:13.394Z",
      "bnb": "2026-01-01T03:11:07.891Z",
      "brl": "2026-02-28T10:15:10.351Z",
      "btc": "2026-03-10T03:01:11.260Z",
      "cad": "2026-03-08T22:30:13.394Z",
      "chf": "2026-02-28T10:15:10.351Z",
      "clp": "2026-02-28T10:15:10.351Z",
      "cny": "2026-02-28T10:15:10.351Z",
      "czk": "2026-02-28T10:15:10.351Z",
      "dkk": "2026-02-28T10:15:10.351Z",
      "dot": "2023-07-13T15:11:22.783Z",
      "eos": "2020-01-30T23:09:35.720Z",
      "eth": "2026-01-19T00:41:23.352Z",
      "eur": "2026-02-28T10:15:10.351Z",
      "gbp": "2026-02-28T10:15:10.351Z",
      "gel": "2026-02-28T10:15:10.351Z",
      "hkd": "2026-03-08T22:30:13.394Z",
      "huf": "2026-02-28T10:15:10.351Z",
      "idr": "2023-09-11T19:42:08.247Z",
      "ils": "2026-03-08T22:30:13.394Z",
      "inr": "2023-09-11T19:42:08.247Z",
      "jpy": "2020-03-13T02:20:48.438Z",
      "krw": "2023-09-11T19:42:08.247Z",
      "kwd": "2026-03-08T22:30:13.394Z",
      "lkr": "2020-03-13T02:20:48.438Z",
      "ltc": "2023-07-13T09:31:11.085Z",
      "mmk": "2020-03-13T02:20:48.438Z",
      "mxn": "2026-02-28T10:15:10.351Z",
      "myr": "2026-02-28T10:15:10.351Z",
      "ngn": "2023-06-10T04:31:46.997Z",
      "nok": "2026-02-28T10:15:10.351Z",
      "nzd": "2026-02-28T10:15:10.351Z",
      "php": "2026-02-28T10:15:10.351Z",
      "pkr": "2020-03-13T02:20:48.438Z",
      "pln": "2026-02-28T10:15:10.351Z",
      "rub": "2026-02-28T10:15:10.351Z",
      "sar": "2026-03-08T22:30:13.394Z",
      "sek": "2026-02-28T10:15:10.351Z",
      "sgd": "2026-02-28T10:15:10.351Z",
      "sol": "2025-10-10T21:28:02.477Z",
      "thb": "2026-02-28T10:15:10.351Z",
      "try": "2020-03-13T02:20:48.438Z",
      "twd": "2026-02-28T10:15:10.351Z",
      "uah": "2020-03-13T02:20:48.438Z",
      "usd": "2026-03-08T22:30:13.394Z",
      "vef": "2026-03-08T22:30:13.394Z",
      "vnd": "2023-09-11T19:42:08.247Z",
      "xag": "2026-02-02T09:20:34.960Z",
      "xau": "2026-02-28T10:15:10.351Z",
      "xdr": "2026-02-28T10:15:10.351Z",
      "xlm": "2024-11-24T20:35:33.590Z",
      "xrp": "2025-12-22T07:53:26.131Z",
      "yfi": "2020-09-15T16:12:32.685Z",
      "zar": "2026-02-28T10:15:10.351Z",
      "bits": "2026-03-10T03:01:11.260Z",
      "link": "2023-11-10T16:30:38.735Z",
      "sats": "2026-03-10T03:01:11.260Z"
    },
    "market_cap": {
      "aed": 3000220084,
      "ars": 1139507888678,
      "aud": 1168897182,
      "bch": 1746368,
      "bdt": 100238240207,
      "bhd": 310479685,
      "bmd": 816942160,
      "bnb": 1231536,
      "brl": 4355036963,
      "btc": 11367,
      "cad": 1128237971,
      "chf": 650245930,
      "clp": 749488220819,
      "cny": 5634123303,
      "czk": 17507233886,
      "dkk": 5346968134,
      "dot": 570494539,
      "eos": 10022734456,
      "eth": 385306,
      "eur": 712646423,
      "gbp": 617165491,
      "gel": 2230252098,
      "hkd": 6397024740,
      "huf": 278748352551,
      "idr": 13855379887333,
      "ils": 2568923640,
      "inr": 75636467378,
      "jpy": 130502463857,
      "krw": 1227659831527,
      "kwd": 250862514,
      "lkr": 254231772085,
      "ltc": 14735333,
      "mmk": 1715423317810,
      "mxn": 14664275167,
      "myr": 3217526699,
      "ngn": 1132160584563,
      "nok": 7962098022,
      "nzd": 1414129330,
      "php": 48679131694,
      "pkr": 228090723374,
      "pln": 3036992285,
      "rub": 65279578571,
      "sar": 3065930827,
      "sek": 7745183540,
      "sgd": 1046911379,
      "sol": 9217718,
      "thb": 26345573449,
      "try": 36080249697,
      "twd": 26269183638,
      "uah": 36023162595,
      "usd": 816942160,
      "vef": 81800419,
      "vnd": 21481532178611,
      "xag": 10134633,
      "xau": 162735,
      "xdr": 581072986,
      "xlm": 4860617661,
      "xrp": 576690024,
      "yfi": 316127,
      "zar": 13792360969,
      "bits": 11367333156,
      "link": 87994094,
      "sats": 1136733315563
    },
    "market_cap_rank": 78,
    "market_cap_rank_with_rehypothecated": 103,
    "fully_diluted_valuation": {
      "aed": 3000227149,
      "ars": 1139510572006,
      "aud": 1168899934,
      "bch": 1746372,
      "bdt": 100238476249,
      "bhd": 310480416,
      "bmd": 816944084,
      "bnb": 1231539,
      "brl": 4355047218,
      "btc": 11367,
      "cad": 1128240627,
      "chf": 650247461,
      "clp": 749489985724,
      "cny": 5634136571,
      "czk": 17507275112,
      "dkk": 5346980725,
      "dot": 570495882,
      "eos": 10022758058,
      "eth": 385307,
      "eur": 712648101,
      "gbp": 617166944,
      "gel": 2230257350,
      "hkd": 6397039804,
      "huf": 278749008951,
      "idr": 13855412514159,
      "ils": 2568929689,
      "inr": 75636645488,
      "jpy": 130502771166,
      "krw": 1227662722436,
      "kwd": 250863105,
      "lkr": 254232370753,
      "ltc": 14735368,
      "mmk": 1715427357311,
      "mxn": 14664309699,
      "myr": 3217534275,
      "ngn": 1132163250589,
      "nok": 7962116772,
      "nzd": 1414132660,
      "php": 48679246324,
      "pkr": 228091260485,
      "pln": 3036999436,
      "rub": 65279732293,
      "sar": 3065938046,
      "sek": 7745201778,
      "sgd": 1046913844,
      "sol": 9217740,
      "thb": 26345635488,
      "try": 36080334659,
      "twd": 26269245497,
      "uah": 36023247423,
      "usd": 816944084,
      "vef": 81800611,
      "vnd": 21481582763597,
      "xag": 10134657,
      "xau": 162735,
      "xdr": 581074354,
      "xlm": 4860629107,
      "xrp": 576691382,
      "yfi": 316128,
      "zar": 13792393448,
      "bits": 11367359924,
      "link": 87994301,
      "sats": 1136735992357
    },
    "market_cap_fdv_ratio": 1,
    "total_volume": {
      "aed": 101384199,
      "ars": 38506540093,
      "aud": 39499671,
      "bch": 58996,
      "bdt": 3387276081,
      "bhd": 10491808,
      "bmd": 27606317,
      "bnb": 41622,
      "brl": 147166516,
      "btc": 384.263,
      "cad": 38125704,
      "chf": 21973276,
      "clp": 25326896383,
      "cny": 190389726,
      "czk": 591608896,
      "dkk": 180686106,
      "dot": 19294208,
      "eos": 338810392,
      "eth": 13025,
      "eur": 24081929,
      "gbp": 20855413,
      "gel": 75365246,
      "hkd": 216169885,
      "huf": 9419535152,
      "idr": 468204517439,
      "ils": 86809720,
      "inr": 2555926723,
      "jpy": 4409972416,
      "krw": 41485392943,
      "kwd": 8477210,
      "lkr": 8591064636,
      "ltc": 498072,
      "mmk": 57968020599,
      "mxn": 495538912,
      "myr": 108727480,
      "ngn": 38258258126,
      "nok": 269057239,
      "nzd": 47786618,
      "php": 1644977586,
      "pkr": 7707699676,
      "pln": 102626815,
      "rub": 2205944105,
      "sar": 103604713,
      "sek": 261727210,
      "sgd": 35377495,
      "sol": 311677,
      "thb": 890276312,
      "try": 1219232965,
      "twd": 887694928,
      "uah": 1217303863,
      "usd": 27606317,
      "vef": 2764221,
      "vnd": 725909393269,
      "xag": 342472,
      "xau": 5499.18,
      "xdr": 19635766,
      "xlm": 164341720,
      "xrp": 19493828,
      "yfi": 10685,
      "zar": 466074966,
      "bits": 384263458,
      "link": 2974100,
      "sats": 38426345777
    },
    "high_24h": {
      "aed": 0.338706,
      "ars": 128.64,
      "aud": 0.131961,
      "bch": 0.00020054,
      "bdt": 11.32,
      "bhd": 0.0350512,
      "bmd": 0.092228,
      "bnb": 0.00014036,
      "brl": 0.491656,
      "btc": 0.0000013,
      "cad": 0.127371,
      "chf": 0.073409,
      "clp": 84.61,
      "cny": 0.636057,
      "czk": 1.98,
      "dkk": 0.603639,
      "dot": 0.06473176,
      "eos": 1.187519,
      "eth": 0.00004422,
      "eur": 0.080453,
      "gbp": 0.069674,
      "gel": 0.251781,
      "hkd": 0.722184,
      "huf": 31.5,
      "idr": 1564.19,
      "ils": 0.290015,
      "inr": 8.54,
      "jpy": 14.73,
      "krw": 138.6,
      "kwd": 0.0283208,
      "lkr": 28.7,
      "ltc": 0.00167994,
      "mmk": 193.66,
      "mxn": 1.66,
      "myr": 0.363239,
      "ngn": 127.81,
      "nok": 0.898871,
      "nzd": 0.159646,
      "php": 5.5,
      "pkr": 25.75,
      "pln": 0.343155,
      "rub": 7.37,
      "sar": 0.346124,
      "sek": 0.874382,
      "sgd": 0.11819,
      "sol": 0.00105501,
      "thb": 2.97,
      "try": 4.07,
      "twd": 2.97,
      "uah": 4.07,
      "usd": 0.092228,
      "vef": 0.00923475,
      "vnd": 2425.13,
      "xag": 0.00114414,
      "xau": 0.00001837,
      "xdr": 0.065599,
      "xlm": 0.56161801,
      "xrp": 0.06580905,
      "yfi": 0.00003626,
      "zar": 1.56,
      "bits": 1.3,
      "link": 0.01021574,
      "sats": 129.63
    },
    "low_24h": {
      "aed": 0.328391,
      "ars": 124.73,
      "aud": 0.127942,
      "bch": 0.00019212,
      "bdt": 10.97,
      "bhd": 0.03383609,
      "bmd": 0.089419,
      "bnb": 0.00013579,
      "brl": 0.476683,
      "btc": 0.00000125,
      "cad": 0.123492,
      "chf": 0.071173,
      "clp": 82.04,
      "cny": 0.616686,
      "czk": 1.92,
      "dkk": 0.585255,
      "dot": 0.06298025,
      "eos": 1.110313,
      "eth": 0.00004248,
      "eur": 0.078003,
      "gbp": 0.067552,
      "gel": 0.244113,
      "hkd": 0.70019,
      "huf": 30.77,
      "idr": 1516.55,
      "ils": 0.281183,
      "inr": 8.28,
      "jpy": 14.28,
      "krw": 134.37,
      "kwd": 0.02749003,
      "lkr": 27.83,
      "ltc": 0.00161901,
      "mmk": 187.76,
      "mxn": 1.61,
      "myr": 0.352176,
      "ngn": 123.92,
      "nok": 0.871496,
      "nzd": 0.154784,
      "php": 5.33,
      "pkr": 24.97,
      "pln": 0.335134,
      "rub": 7.15,
      "sar": 0.335583,
      "sek": 0.847753,
      "sgd": 0.11459,
      "sol": 0.00101446,
      "thb": 2.88,
      "try": 3.95,
      "twd": 2.88,
      "uah": 3.94,
      "usd": 0.089419,
      "vef": 0.00895351,
      "vnd": 2351.27,
      "xag": 0.00110929,
      "xau": 0.00001781,
      "xdr": 0.063602,
      "xlm": 0.53363379,
      "xrp": 0.06317253,
      "yfi": 0.0000346,
      "zar": 1.51,
      "bits": 1.25,
      "link": 0.00972227,
      "sats": 124.99
    },
    "price_change_24h": 0.00065435,
    "price_change_percentage_24h": 0.71756,
    "price_change_percentage_7d": 10.60526,
    "price_change_percentage_14d": 4.74189,
    "price_change_percentage_30d": 0.6071,
    "price_change_percentage_60d": -33.81891,
    "price_change_percentage_200d": -63.57007,
    "price_change_percentage_1y": -54.29486,
    "market_cap_change_24h": 6356161,
    "market_cap_change_percentage_24h": 0.78414,
    "price_change_24h_in_currency": {
      "aed": 0.00240309,
      "ars": 0.864101,
      "aud": 0.00093625,
      "bch": -0.000004012237803025,
      "bdt": 0.080288,
      "bhd": 0.00039924,
      "bmd": 0.00065435,
      "bnb": -0.000001717989740976,
      "brl": 0.00348827,
      "btc": -1.6394893314e-8,
      "cad": 0.00090369,
      "chf": 0.00075856,
      "clp": 0.60032,
      "cny": 0.00451278,
      "czk": 0.01402282,
      "dkk": 0.00428278,
      "dot": 0.00049469,
      "eos": -0.04744219806813388,
      "eth": -8.57279852279e-7,
      "eur": 0.00057081,
      "gbp": 0.00050993,
      "gel": 0.00178637,
      "hkd": 0.00512384,
      "huf": -0.03748709198122668,
      "idr": 11.1,
      "ils": 0.00205764,
      "inr": 0.064627,
      "jpy": 0.104533,
      "krw": 1.099,
      "kwd": 0.00016856,
      "lkr": 0.203633,
      "ltc": -0.000017610540803881,
      "mmk": 1.37,
      "mxn": 0.01174569,
      "myr": 0.00257715,
      "ngn": 0.90683,
      "nok": 0.00637742,
      "nzd": 0.00109173,
      "php": 0.03899066,
      "pkr": 0.182694,
      "pln": -0.000340197733671554,
      "rub": 0.052287,
      "sar": 0.00245573,
      "sek": 0.00620368,
      "sgd": 0.00083855,
      "sol": -0.000014843407340458,
      "thb": -0.005771461473946804,
      "try": 0.0288993,
      "twd": 0.0210409,
      "uah": 0.02885357,
      "usd": 0.00065435,
      "vef": 0.00006552,
      "vnd": 17.21,
      "xag": 0.00000812,
      "xau": 1.30346e-7,
      "xdr": 0.00046542,
      "xlm": -0.01454867122160175,
      "xrp": -0.000767845926735414,
      "yfi": -6.1376425301e-7,
      "zar": 0.01104731,
      "bits": -0.01639489331392796,
      "link": -0.000313045079849571,
      "sats": -1.6394893313928094
    },
    "price_change_percentage_1h_in_currency": {
      "aed": -0.15751,
      "ars": -0.15751,
      "aud": -0.15751,
      "bch": -0.3233,
      "bdt": -0.15751,
      "bhd": -0.15751,
      "bmd": -0.15751,
      "bnb": 0.02977,
      "brl": -0.15751,
      "btc": -0.13887,
      "cad": -0.15751,
      "chf": -0.15751,
      "clp": -0.15751,
      "cny": -0.15751,
      "czk": -0.15751,
      "dkk": -0.15751,
      "dot": -0.75841,
      "eos": -0.71785,
      "eth": -0.24215,
      "eur": -0.15751,
      "gbp": -0.15751,
      "gel": -0.15751,
      "hkd": -0.15751,
      "huf": -0.15751,
      "idr": -0.15751,
      "ils": -0.15751,
      "inr": -0.15751,
      "jpy": -0.15751,
      "krw": -0.15751,
      "kwd": -0.15751,
      "lkr": -0.15751,
      "ltc": -0.10062,
      "mmk": -0.15751,
      "mxn": -0.15751,
      "myr": -0.15751,
      "ngn": -0.15751,
      "nok": -0.15751,
      "nzd": -0.15751,
      "php": -0.15751,
      "pkr": -0.15751,
      "pln": -0.15751,
      "rub": -0.15751,
      "sar": -0.15751,
      "sek": -0.15751,
      "sgd": -0.15751,
      "sol": -0.02471,
      "thb": -0.15752,
      "try": -0.15751,
      "twd": -0.15751,
      "uah": -0.15751,
      "usd": -0.15751,
      "vef": -0.15751,
      "vnd": -0.15751,
      "xag": -0.15751,
      "xau": -0.15751,
      "xdr": -0.15751,
      "xlm": -0.02285,
      "xrp": -0.10931,
      "yfi": -0.02204,
      "zar": -0.15751,
      "bits": -0.13887,
      "link": 0.0594,
      "sats": -0.13887
    },
    "price_change_percentage_24h_in_currency": {
      "aed": 0.71756,
      "ars": 0.67908,
      "aud": 0.71756,
      "bch": -2.00323,
      "bdt": 0.71756,
      "bhd": 1.157,
      "bmd": 0.71756,
      "bnb": -1.22545,
      "brl": 0.71756,
      "btc": -1.26619,
      "cad": 0.71756,
      "chf": 1.04853,
      "clp": 0.71756,
      "cny": 0.71756,
      "czk": 0.71756,
      "dkk": 0.71756,
      "dot": 0.77664,
      "eos": -4.03883,
      "eth": -1.94002,
      "eur": 0.71756,
      "gbp": 0.74036,
      "gel": 0.71756,
      "hkd": 0.71756,
      "huf": -0.11948,
      "idr": 0.71756,
      "ils": 0.71756,
      "inr": 0.76583,
      "jpy": 0.71759,
      "krw": 0.80275,
      "kwd": 0.60126,
      "lkr": 0.71756,
      "ltc": -1.05158,
      "mmk": 0.71756,
      "mxn": 0.71756,
      "myr": 0.71756,
      "ngn": 0.71756,
      "nok": 0.71756,
      "nzd": 0.69144,
      "php": 0.71756,
      "pkr": 0.71756,
      "pln": -0.09954,
      "rub": 0.71756,
      "sar": 0.71756,
      "sek": 0.71756,
      "sgd": 0.71756,
      "sol": -1.41126,
      "thb": -0.19448,
      "try": 0.71756,
      "twd": 0.71756,
      "uah": 0.71756,
      "usd": 0.71756,
      "vef": 0.71756,
      "vnd": 0.71756,
      "xag": 0.71756,
      "xau": 0.71756,
      "xdr": 0.71756,
      "xlm": -2.59193,
      "xrp": -1.17009,
      "yfi": -1.69719,
      "zar": 0.71756,
      "bits": -1.26619,
      "link": -3.06674,
      "sats": -1.26619
    },
    "price_change_percentage_7d_in_currency": {
      "aed": 10.60526,
      "ars": 8.64047,
      "aud": 11.38074,
      "bch": 6.55613,
      "bdt": 11.56091,
      "bhd": 11.97142,
      "bmd": 10.60526,
      "bnb": 3.45411,
      "brl": 12.41777,
      "btc": 4.27204,
      "cad": 12.50332,
      "chf": 13.37076,
      "clp": 11.33841,
      "cny": 10.60205,
      "czk": 12.91517,
      "dkk": 12.56413,
      "dot": 12.65759,
      "eos": 6.96296,
      "eth": 2.47394,
      "eur": 12.08636,
      "gbp": 12.02571,
      "gel": 10.91403,
      "hkd": 10.72474,
      "huf": 11.51595,
      "idr": 10.73682,
      "ils": 12.45631,
      "inr": 11.38048,
      "jpy": 11.97922,
      "krw": 11.90545,
      "kwd": 10.68564,
      "lkr": 11.23049,
      "ltc": 6.52776,
      "mmk": 10.60526,
      "mxn": 11.5511,
      "myr": 10.38804,
      "ngn": 10.9554,
      "nok": 12.48794,
      "nzd": 12.91236,
      "php": 11.62055,
      "pkr": 11.1476,
      "pln": 11.53234,
      "rub": 11.50442,
      "sar": 10.41361,
      "sek": 14.19714,
      "sgd": 11.26075,
      "sol": 3.90956,
      "thb": 12.28516,
      "try": 10.83741,
      "twd": 11.78093,
      "uah": 12.20936,
      "usd": 10.60526,
      "vef": 10.60526,
      "vnd": 10.92497,
      "xag": 16.00207,
      "xau": 13.95173,
      "xdr": 12.09997,
      "xlm": -0.62216,
      "xrp": 6.3792,
      "yfi": 6.21555,
      "zar": 12.86293,
      "bits": 4.27204,
      "link": 3.53147,
      "sats": 4.27204
    },
    "price_change_percentage_14d_in_currency": {
      "aed": 4.74189,
      "ars": 3.89592,
      "aud": 6.6452,
      "bch": 0.06176,
      "bdt": 5.34075,
      "bhd": 5.75449,
      "bmd": 4.74189,
      "bnb": -2.04594,
      "brl": 8.84377,
      "btc": -2.96067,
      "cad": 5.98512,
      "chf": 8.10938,
      "clp": 9.98956,
      "cny": 5.32836,
      "czk": 9.39216,
      "dkk": 8.39874,
      "dot": 15.64512,
      "eos": 3.7915,
      "eth": -1.85463,
      "eur": 7.98095,
      "gbp": 6.44711,
      "gel": 6.69603,
      "hkd": 4.83963,
      "huf": 12.40455,
      "idr": 5.72433,
      "ils": 5.04488,
      "inr": 6.47656,
      "jpy": 7.22547,
      "krw": 9.32135,
      "kwd": 5.33602,
      "lkr": 5.57479,
      "ltc": 2.05947,
      "mmk": 4.7374,
      "mxn": 9.08963,
      "myr": 6.01237,
      "ngn": 6.97582,
      "nok": 7.35262,
      "nzd": 8.72162,
      "php": 8.09146,
      "pkr": 4.80032,
      "pln": 8.98101,
      "rub": 8.43458,
      "sar": 4.88498,
      "sek": 9.95875,
      "sgd": 6.14165,
      "sol": 0.81442,
      "thb": 8.59773,
      "try": 5.32617,
      "twd": 7.29621,
      "uah": 7.29767,
      "usd": 4.74189,
      "vef": 4.74189,
      "vnd": 5.74747,
      "xag": -0.17954,
      "xau": 10.1266,
      "xdr": 7.93826,
      "xlm": -1.21226,
      "xrp": 2.07515,
      "yfi": 8.36466,
      "zar": 11.01772,
      "bits": -2.96067,
      "link": 0.20909,
      "sats": -2.96067
    },
    "price_change_percentage_30d_in_currency": {
      "aed": 0.6071,
      "ars": 0.45361,
      "aud": 1.863,
      "bch": 11.76949,
      "bdt": 0.78219,
      "bhd": 1.42668,
      "bmd": 0.6071,
      "bnb": -8.65497,
      "brl": 2.81253,
      "btc": -6.67312,
      "cad": 2.14401,
      "chf": 4.00957,
      "clp": 7.52763,
      "cny": 0.41781,
      "czk": 5.47695,
      "dkk": 4.56614,
      "dot": -10.11261,
      "eos": 3.82334,
      "eth": -7.05089,
      "eur": 4.11313,
      "gbp": 3.54349,
      "gel": 2.10312,
      "hkd": 0.78768,
      "huf": 7.69026,
      "idr": 1.39374,
      "ils": 2.73511,
      "inr": 2.70213,
      "jpy": 4.64536,
      "krw": 4.63403,
      "kwd": 0.72125,
      "lkr": 1.05018,
      "ltc": -3.19469,
      "mmk": 0.60279,
      "mxn": 4.8779,
      "myr": 1.49617,
      "ngn": 2.79765,
      "nok": 2.9235,
      "nzd": 5.15119,
      "php": 3.30114,
      "pkr": 0.26871,
      "pln": 5.29593,
      "rub": 4.10104,
      "sar": 0.67282,
      "sek": 6.84334,
      "sgd": 2.04327,
      "sol": -9.50209,
      "thb": 4.50723,
      "try": 1.58441,
      "twd": 2.93761,
      "uah": 2.98508,
      "usd": 0.6071,
      "vef": 0.6071,
      "vnd": 1.8502,
      "xag": -1.53374,
      "xau": -0.14482,
      "xdr": 4.0908,
      "xlm": -5.52933,
      "xrp": -2.87268,
      "yfi": 17.05207,
      "zar": 6.11758,
      "bits": -6.67312,
      "link": -8.33274,
      "sats": -6.67312
    },
    "price_change_percentage_60d_in_currency": {
      "aed": -33.81891,
      "ars": -36.71058,
      "aud": -36.59609,
      "bch": -14.74911,
      "bdt": -33.7209,
      "bhd": -33.28915,
      "bmd": -33.81891,
      "bnb": -6.47281,
      "brl": -34.47649,
      "btc": -12.43364,
      "cad": -34.20655,
      "chf": -34.31905,
      "clp": -31.39024,
      "cny": -34.53651,
      "czk": -31.7606,
      "dkk": -32.45434,
      "dot": 5.51156,
      "eos": 46.07236,
      "eth": 3.86623,
      "eur": -32.73122,
      "gbp": -32.72056,
      "gel": -32.70973,
      "hkd": -33.54261,
      "huf": -31.68566,
      "idr": -33.45445,
      "ils": -33.84173,
      "inr": -32.12929,
      "jpy": -33.40933,
      "krw": -32.45795,
      "kwd": -34.00845,
      "lkr": -33.55731,
      "ltc": -5.83541,
      "mmk": -33.82174,
      "mxn": -33.30935,
      "myr": -35.60118,
      "ngn": -35.64023,
      "nok": -36.01595,
      "nzd": -34.15604,
      "php": -33.73327,
      "pkr": -34.16119,
      "pln": -31.93399,
      "rub": -32.5466,
      "sar": -33.77166,
      "sek": -31.86226,
      "sgd": -34.11919,
      "sol": 8.61747,
      "thb": -32.09651,
      "try": -32.28805,
      "twd": -32.6849,
      "uah": -32.51767,
      "usd": -33.81891,
      "vef": -33.81891,
      "vnd": -33.77093,
      "xag": -25.67337,
      "xau": -38.95502,
      "xdr": -32.84397,
      "xlm": -3.88942,
      "xrp": 0.3276,
      "yfi": -7.47343,
      "zar": -31.74389,
      "bits": -12.43364,
      "link": 0.4549,
      "sats": -12.43364
    },
    "price_change_percentage_200d_in_currency": {
      "aed": -63.57007,
      "ars": -62.5252,
      "aud": -66.27405,
      "bch": -56.93568,
      "bdt": -63.3641,
      "bhd": -63.27954,
      "bmd": -63.57007,
      "bnb": -52.99978,
      "brl": -64.3079,
      "btc": -43.88359,
      "cad": -63.67785,
      "chf": -64.04337,
      "clp": -65.4214,
      "cny": -64.9127,
      "czk": -63.10994,
      "dkk": -62.99081,
      "dot": -1.85166,
      "eos": 118.69224,
      "eth": -21.24027,
      "eur": -63.18007,
      "gbp": -63.00028,
      "gel": -63.09696,
      "hkd": -63.36361,
      "huf": -63.65862,
      "idr": -62.3328,
      "ils": -65.81116,
      "inr": -61.60823,
      "jpy": -60.64943,
      "krw": -60.81936,
      "kwd": -63.42022,
      "lkr": -62.50505,
      "ltc": -26.02156,
      "mmk": -63.55602,
      "mxn": -65.06681,
      "myr": -66.1166,
      "ngn": -67.122,
      "nok": -65.1164,
      "nzd": -63.2403,
      "php": -62.06177,
      "pkr": -64.16047,
      "pln": -63.20287,
      "rub": -63.67714,
      "sar": -63.56364,
      "sek": -64.05606,
      "sgd": -63.7665,
      "sol": -16.6563,
      "thb": -63.82359,
      "try": -60.79717,
      "twd": -61.74635,
      "uah": -61.21939,
      "usd": -63.57007,
      "vef": -63.57007,
      "vnd": -63.66329,
      "xag": -82.65654,
      "xau": -75.44382,
      "xdr": -63.03868,
      "xlm": -16.70071,
      "xrp": -22.6565,
      "yfi": -22.73782,
      "zar": -65.31407,
      "bits": -43.88359,
      "link": -5.08728,
      "sats": -43.88359
    },
    "price_change_percentage_1y_in_currency": {
      "aed": -54.29672,
      "ars": -40.07509,
      "aud": -58.61751,
      "bch": -65.67007,
      "bdt": -53.81054,
      "bhd": -53.74769,
      "bmd": -54.29486,
      "bnb": -58.85879,
      "brl": -57.59372,
      "btc": -46.597,
      "cad": -56.12478,
      "chf": -58.88908,
      "clp": -54.9248,
      "cny": -56.45488,
      "czk": -57.41156,
      "dkk": -56.38272,
      "dot": 37.66152,
      "eos": 181.52301,
      "eth": -58.52973,
      "eur": -56.4598,
      "gbp": -55.31345,
      "gel": -55.03602,
      "hkd": -53.96919,
      "huf": -57.51022,
      "idr": -52.52563,
      "ils": -60.58881,
      "inr": -51.33095,
      "jpy": -50.88183,
      "krw": -52.66629,
      "kwd": -54.27818,
      "lkr": -51.89946,
      "ltc": -22.9619,
      "mmk": -54.25543,
      "mxn": -58.832,
      "myr": -59.51654,
      "ngn": -58.63943,
      "nok": -58.58397,
      "nzd": -54.48868,
      "php": -52.48888,
      "pkr": -54.33803,
      "pln": -55.77975,
      "rub": -57.13055,
      "sar": -54.27089,
      "sek": -57.22194,
      "sgd": -56.20849,
      "sol": -30.91894,
      "thb": -56.0144,
      "try": -44.895,
      "twd": -55.38473,
      "uah": -51.30144,
      "usd": -54.29486,
      "vef": -54.29486,
      "vnd": -52.89473,
      "xag": -80.85566,
      "xau": -72.80788,
      "xdr": -56.47462,
      "xlm": -25.44207,
      "xrp": -22.28541,
      "yfi": -9.68228,
      "zar": -57.60157,
      "bits": -46.597,
      "link": -31.53371,
      "sats": -46.597
    },
    "market_cap_change_24h_in_currency": {
      "aed": 23343002,
      "ars": 8433734753,
      "aud": 9094523,
      "bch": -34694.73000156437,
      "bdt": 779896614,
      "bhd": 3753943,
      "bmd": 6356161,
      "bnb": -15080.092170025688,
      "brl": 33884060,
      "btc": -142.28330280503178,
      "cad": 8778177,
      "chf": 7172391,
      "clp": 5831340657,
      "cny": 43835902,
      "czk": 136213808,
      "dkk": 41601711,
      "dot": 3956652,
      "eos": -418669144.048254,
      "eth": -7514.379005154537,
      "eur": 5544696,
      "gbp": 4940423,
      "gel": 17352320,
      "hkd": 49771603,
      "huf": -149061863.20892334,
      "idr": 107800813693,
      "ils": 19987331,
      "inr": 624433731,
      "jpy": 1015403434,
      "krw": 10581165633,
      "kwd": 1664060,
      "lkr": 1978032513,
      "ltc": -157305.27101386152,
      "mmk": 13346731089,
      "mxn": 114094367,
      "myr": 25033741,
      "ngn": 8808696206,
      "nok": 61948547,
      "nzd": 10638581,
      "php": 378744578,
      "pkr": 1774643913,
      "pln": -1017571.9292135239,
      "rub": 507903193,
      "sar": 23854260,
      "sek": 60260859,
      "sgd": 8145421,
      "sol": -133992.3423938807,
      "thb": -33896560.87575531,
      "try": 280719858,
      "twd": 204385545,
      "uah": 280275696,
      "usd": 6356161,
      "vef": 636442,
      "vnd": 167135557961,
      "xag": 78852,
      "xau": 1266.15,
      "xdr": 4520998,
      "xlm": -130778085.63948822,
      "xrp": -6895407.601191282,
      "yfi": -5444.701795459143,
      "zar": 107310499,
      "bits": -142283302.80503273,
      "link": -2793789.9500946105,
      "sats": -14228330280.503174
    },
    "market_cap_change_percentage_24h_in_currency": {
      "aed": 0.78414,
      "ars": 0.74564,
      "aud": 0.78414,
      "bch": -1.94798,
      "bdt": 0.78414,
      "bhd": 1.22388,
      "bmd": 0.78414,
      "bnb": -1.20968,
      "brl": 0.78414,
      "btc": -1.23621,
      "cad": 0.78414,
      "chf": 1.11533,
      "clp": 0.78414,
      "cny": 0.78414,
      "czk": 0.78414,
      "dkk": 0.78414,
      "dot": 0.69839,
      "eos": -4.0097,
      "eth": -1.91293,
      "eur": 0.78414,
      "gbp": 0.80696,
      "gel": 0.78414,
      "hkd": 0.78414,
      "huf": -0.05345,
      "idr": 0.78414,
      "ils": 0.78414,
      "inr": 0.83244,
      "jpy": 0.78417,
      "krw": 0.86939,
      "kwd": 0.66777,
      "lkr": 0.78414,
      "ltc": -1.05626,
      "mmk": 0.78414,
      "mxn": 0.78414,
      "myr": 0.78414,
      "ngn": 0.78414,
      "nok": 0.78414,
      "nzd": 0.75801,
      "php": 0.78414,
      "pkr": 0.78414,
      "pln": -0.03349,
      "rub": 0.78414,
      "sar": 0.78414,
      "sek": 0.78414,
      "sgd": 0.78414,
      "sol": -1.43281,
      "thb": -0.1285,
      "try": 0.78414,
      "twd": 0.78414,
      "uah": 0.78414,
      "usd": 0.78414,
      "vef": 0.78414,
      "vnd": 0.78414,
      "xag": 0.78414,
      "xau": 0.78414,
      "xdr": 0.78414,
      "xlm": -2.62007,
      "xrp": -1.18156,
      "yfi": -1.69315,
      "zar": 0.78414,
      "bits": -1.23621,
      "link": -3.07727,
      "sats": -1.23621
    },
    "total_supply": 8890219020.174583,
    "max_supply": 10000000000,
    "max_supply_infinite": false,
    "circulating_supply": 8890198085.422396,
    "last_updated": "2026-03-15T10:32:36.350Z"
  },
  "community_data": {
    "facebook_likes": null,
    "reddit_average_posts_48h": 0,
    "reddit_average_comments_48h": 0,
    "reddit_subscribers": 0,
    "reddit_accounts_active_48h": 0,
    "telegram_channel_user_count": 21733
  },
  "developer_data": {
    "forks": 521,
    "stars": 1427,
    "subscribers": 69,
    "total_issues": 0,
    "closed_issues": 0,
    "pull_requests_merged": 3898,
    "pull_request_contributors": 115,
    "code_additions_deletions_4_weeks": {
      "additions": 6470,
      "deletions": -5388
    },
    "commit_count_4_weeks": 20,
    "last_4_weeks_commit_activity_series": [
      0,
      0,
      0,
      0,
      0,
      0,
      0,
      0,
      1,
      2,
      4,
      1,
      2,
      0,
      0,
      1,
      0,
      0,
      2,
      1,
      0,
      0,
      0,
      3,
      0,
      1,
      2,
      0
    ]
  },
  "status_updates": [],
  "last_updated": "2026-03-15T10:32:36.350Z"
}