{
  "id": "arbitrum",
  "symbol": "arb",
  "name": "Arbitrum",
  "market": {
    "price": 0.108695,
    "marketCap": 645547076,
    "marketCapRank": 88,
    "volume24h": 73578826,
    "priceChange24h": 6.78225,
    "ath": 2.39,
    "athChangePercentage": -95.41372,
    "athDate": "2024-01-12T12:29:59.231Z",
    "atl": 0.088935,
    "atlDate": "2026-02-23T01:30:53.292Z",
    "circulatingSupply": 5939074958,
    "totalSupply": 10000000000,
    "maxSupply": 10000000000
  },
  "lastMarketUpdate": "2026-03-16T08:38:53.880Z"
}