{
  "id": "berachain-bera",
  "symbol": "bera",
  "name": "Berachain",
  "market": {
    "price": 0.649364,
    "marketCap": 148915149,
    "marketCapRank": 217,
    "volume24h": 20469400,
    "priceChange24h": -1.76231,
    "ath": 14.83,
    "athChangePercentage": -95.61583,
    "athDate": "2025-02-06T14:16:01.862Z",
    "atl": 0.349389,
    "atlDate": "2026-02-06T00:25:15.713Z",
    "circulatingSupply": 229301574.182873,
    "totalSupply": 534786093.2212218,
    "maxSupply": null
  },
  "lastMarketUpdate": "2026-03-18T07:19:53.398Z"
}