{
  "id": "bittorrent",
  "symbol": "btt",
  "name": "BitTorrent",
  "market": {
    "price": 3.49621e-7,
    "marketCap": 345406442,
    "marketCapRank": 122,
    "volume24h": 102520401,
    "priceChange24h": 0.75039,
    "ath": 0.00000343,
    "athChangePercentage": -89.8005,
    "athDate": "2022-01-21T04:00:31.909Z",
    "atl": 3.04531e-7,
    "atlDate": "2026-02-06T04:10:19.280Z",
    "circulatingSupply": 987037885840674.8,
    "totalSupply": 990000000000000,
    "maxSupply": 990000000000000
  },
  "lastMarketUpdate": "2026-03-17T19:06:40.996Z"
}