{
  "id": "bonk",
  "symbol": "bonk",
  "name": "Bonk",
  "market": {
    "price": 0.00000663,
    "marketCap": 583364626,
    "marketCapRank": 93,
    "volume24h": 100891427,
    "priceChange24h": 10.6742,
    "ath": 0.00005825,
    "athChangePercentage": -88.3679,
    "athDate": "2024-11-20T04:01:06.465Z",
    "atl": 8.6142e-8,
    "atlDate": "2022-12-29T22:48:46.755Z",
    "circulatingSupply": 87994758035375.45,
    "totalSupply": 87994758035916.42,
    "maxSupply": 87995282867000.55
  },
  "lastMarketUpdate": "2026-03-16T08:38:53.883Z"
}