{
  "id": "btse-token",
  "symbol": "btse",
  "name": "BTSE Token",
  "market": {
    "price": 1.53,
    "marketCap": 248005190,
    "marketCapRank": 157,
    "volume24h": 5185177,
    "priceChange24h": 2.17743,
    "ath": 9.21,
    "athChangePercentage": -83.40162,
    "athDate": "2022-03-23T09:11:07.549Z",
    "atl": 0.06191,
    "atlDate": "2025-10-10T22:48:11.249Z",
    "circulatingSupply": 162061501,
    "totalSupply": 200000000,
    "maxSupply": 200000000
  },
  "lastMarketUpdate": "2026-03-17T19:06:41.006Z"
}