{
  "id": "chain-2",
  "symbol": "xcn",
  "name": "Onyxcoin",
  "market": {
    "price": 0.00595907,
    "marketCap": 222959541,
    "marketCapRank": 167,
    "volume24h": 39915306,
    "priceChange24h": 7.7652,
    "ath": 0.184139,
    "athChangePercentage": -96.76737,
    "athDate": "2022-05-27T11:45:24.820Z",
    "atl": 0.0007055,
    "atlDate": "2023-10-11T20:12:02.910Z",
    "circulatingSupply": 37467266395.40625,
    "totalSupply": 53402432357.48609,
    "maxSupply": 68892071756.9
  },
  "lastMarketUpdate": "2026-03-16T08:38:53.914Z"
}