{
  "id": "cow-protocol",
  "symbol": "cow",
  "name": "CoW Protocol",
  "market": {
    "price": 0.215601,
    "marketCap": 120664554,
    "marketCapRank": 239,
    "volume24h": 5127730,
    "priceChange24h": -4.75914,
    "ath": 2.22,
    "athChangePercentage": -90.27897,
    "athDate": "2022-03-28T16:24:17.921Z",
    "atl": 0.03987045,
    "atlDate": "2022-11-09T18:32:42.225Z",
    "circulatingSupply": 559277516.9864178,
    "totalSupply": 1000000000,
    "maxSupply": 1000000000
  },
  "lastMarketUpdate": "2026-03-22T15:45:10.146Z"
}