{
  "id": "crypto-com-chain",
  "symbol": "cro",
  "name": "Cronos",
  "description": "",
  "categories": [],
  "genesisDate": null,
  "links": {
    "website": null,
    "github": null,
    "reddit": null,
    "explorer": null
  },
  "market": {
    "price": 0.075195,
    "marketCap": 3180042079,
    "marketCapRank": 32,
    "volume24h": 7637449,
    "high24h": 0,
    "low24h": 0,
    "priceChange24h": -0.02047,
    "priceChange7d": 0,
    "priceChange30d": 0,
    "priceChange1y": 0,
    "ath": 0.891544,
    "athChangePercentage": -91.56326,
    "athDate": "2021-11-24T00:00:00.000Z",
    "atl": 0.0121196,
    "atlDate": "2019-02-08T00:00:00.000Z",
    "circulatingSupply": 42288979526.11902,
    "totalSupply": 98489004802.04063,
    "maxSupply": 100000000000,
    "fdv": null
  },
  "community": {
    "twitterFollowers": null,
    "redditSubscribers": null
  },
  "developer": {
    "githubStars": null,
    "githubForks": null,
    "commits4Weeks": null
  },
  "fetchedAt": "2026-03-15T10:11:56.505Z",
  "lastMarketUpdate": "2026-03-21T21:49:10.793Z"
}