{
  "id": "dai",
  "symbol": "dai",
  "name": "Dai",
  "description": "",
  "categories": [],
  "genesisDate": null,
  "links": {
    "website": null,
    "github": null,
    "reddit": null,
    "explorer": null
  },
  "market": {
    "price": 0.99991,
    "marketCap": 4316517800,
    "marketCapRank": 23,
    "volume24h": 142501715,
    "high24h": 0,
    "low24h": 0,
    "priceChange24h": 0.00693,
    "priceChange7d": 0,
    "priceChange30d": 0,
    "priceChange1y": 0,
    "ath": 1.22,
    "athChangePercentage": -17.96572,
    "athDate": "2020-03-13T03:02:50.373Z",
    "atl": 0.88196,
    "atlDate": "2023-03-11T07:50:50.514Z",
    "circulatingSupply": 4316911034.141481,
    "totalSupply": 4316911034.141481,
    "maxSupply": null,
    "fdv": null
  },
  "community": {
    "twitterFollowers": null,
    "redditSubscribers": null
  },
  "developer": {
    "githubStars": null,
    "githubForks": null,
    "commits4Weeks": null
  },
  "fetchedAt": "2026-03-15T10:11:56.500Z",
  "lastMarketUpdate": "2026-03-22T13:57:46.838Z"
}