{
  "id": "ethereum-name-service",
  "symbol": "ens",
  "name": "Ethereum Name Service",
  "market": {
    "price": 6.79,
    "marketCap": 260734987,
    "marketCapRank": 154,
    "volume24h": 50131781,
    "priceChange24h": 2.94887,
    "ath": 83.4,
    "athChangePercentage": -91.85854,
    "athDate": "2021-11-11T02:20:01.099Z",
    "atl": 5.01,
    "atlDate": "2026-02-06T00:25:50.342Z",
    "circulatingSupply": 38380013.53099827,
    "totalSupply": 100000000,
    "maxSupply": 100000000
  },
  "lastMarketUpdate": "2026-03-17T19:06:41.005Z"
}