{
  "id": "fartcoin",
  "symbol": "fartcoin",
  "name": "Fartcoin",
  "market": {
    "price": 0.188786,
    "marketCap": 188925766,
    "marketCapRank": 177,
    "volume24h": 31990315,
    "priceChange24h": -4.15372,
    "ath": 2.48,
    "athChangePercentage": -92.38453,
    "athDate": "2025-01-19T20:41:07.782Z",
    "atl": 0.02002855,
    "atlDate": "2024-10-30T07:56:04.381Z",
    "circulatingSupply": 999978889.622304,
    "totalSupply": 999978889.622304,
    "maxSupply": 1000000000
  },
  "lastMarketUpdate": "2026-03-22T15:45:10.126Z"
}