{
  "id": "filecoin",
  "symbol": "fil",
  "name": "Filecoin",
  "market": {
    "price": 0.887551,
    "marketCap": 678070578,
    "marketCapRank": 85,
    "volume24h": 67819393,
    "priceChange24h": -3.8452,
    "ath": 236.84,
    "athChangePercentage": -99.62442,
    "athDate": "2021-04-01T13:29:41.564Z",
    "atl": 0.812608,
    "atlDate": "2026-02-06T00:30:17.896Z",
    "circulatingSupply": 762428874,
    "totalSupply": 1957976044,
    "maxSupply": null
  },
  "lastMarketUpdate": "2026-03-19T18:08:38.787Z"
}