{
  "id": "gusd",
  "symbol": "gusd",
  "name": "GUSD",
  "market": {
    "price": 1.001,
    "marketCap": 149989326,
    "marketCapRank": 217,
    "volume24h": 1010897,
    "priceChange24h": 0.20531,
    "ath": 1.022,
    "athChangePercentage": -2.00224,
    "athDate": "2026-03-02T15:10:22.864Z",
    "atl": 0.979237,
    "atlDate": "2026-03-02T17:40:29.971Z",
    "circulatingSupply": 149790000,
    "totalSupply": 320000000,
    "maxSupply": 320000000
  },
  "lastMarketUpdate": "2026-03-17T07:31:31.303Z"
}