{
  "id": "hastra-prime",
  "symbol": "prime",
  "name": "PRIME",
  "market": {
    "price": 1.026,
    "marketCap": 326509087,
    "marketCapRank": 129,
    "volume24h": 153860,
    "priceChange24h": -0.01674,
    "ath": 1.5,
    "athChangePercentage": -31.52497,
    "athDate": "2026-03-11T15:16:40.298Z",
    "atl": 0.992801,
    "atlDate": "2025-12-07T10:18:14.905Z",
    "circulatingSupply": 318303984.548639,
    "totalSupply": 318303984.548639,
    "maxSupply": null
  },
  "lastMarketUpdate": "2026-03-16T08:38:53.899Z"
}