{
  "id": "hastra-prime",
  "symbol": "prime",
  "name": "PRIME",
  "market": {
    "price": 1.029,
    "marketCap": 354465035,
    "marketCapRank": 120,
    "volume24h": 766982,
    "priceChange24h": 0.06696,
    "ath": 1.5,
    "athChangePercentage": -31.41061,
    "athDate": "2026-03-11T15:16:40.298Z",
    "atl": 0.956408,
    "atlDate": "2026-03-17T16:35:52.023Z",
    "circulatingSupply": 344484895.299539,
    "totalSupply": 344484895.299539,
    "maxSupply": null
  },
  "lastMarketUpdate": "2026-03-21T23:29:40.346Z"
}