{
  "id": "injective-protocol",
  "symbol": "inj",
  "name": "Injective",
  "market": {
    "price": 2.99,
    "marketCap": 299554229,
    "marketCapRank": 130,
    "volume24h": 35766616,
    "priceChange24h": -2.96476,
    "ath": 52.62,
    "athChangePercentage": -94.30727,
    "athDate": "2024-03-14T15:06:22.124Z",
    "atl": 0.657401,
    "atlDate": "2020-11-03T16:19:30.576Z",
    "circulatingSupply": 100000000,
    "totalSupply": 100000000,
    "maxSupply": null
  },
  "lastMarketUpdate": "2026-03-19T18:08:38.796Z"
}