{
  "id": "jito-governance-token",
  "symbol": "jto",
  "name": "Jito",
  "market": {
    "price": 0.285567,
    "marketCap": 128551691,
    "marketCapRank": 225,
    "volume24h": 8808261,
    "priceChange24h": -6.69298,
    "ath": 6.01,
    "athChangePercentage": -95.24179,
    "athDate": "2023-12-07T16:04:48.717Z",
    "atl": 0.218137,
    "atlDate": "2026-02-06T00:30:39.402Z",
    "circulatingSupply": 450169772.7,
    "totalSupply": 1000000000,
    "maxSupply": null
  },
  "lastMarketUpdate": "2026-03-22T13:57:46.892Z"
}