{
  "id": "kaspa",
  "symbol": "kas",
  "name": "Kaspa",
  "description": "Kaspa was fair-launched in November 2021 with no pre-mine, zero pre-sale, and no coin allocations, and is 100 percent community-managed. Kaspa aims to be the world's global sequencer for traditional finance and decentralized crypto markets by utilizing proof-of-work and its BlockDAG consensus protocol, GHOSTDAG. Being the world's fastest proof-of-work network, Kaspa combines five properties: (1) hard money principles, (2) Bitcoin's ethos of security-first fundamentals (boasting a security...",
  "categories": [
    "Smart Contract Platform",
    "Layer 1 (L1)",
    "Wallets",
    "Proof of Work (PoW)",
    "Kaspa Ecosystem",
    "Made in USA",
    "Directed Acyclic Graph (DAG)"
  ],
  "genesisDate": null,
  "links": {
    "website": "https://kaspa.org/",
    "github": "https://github.com/kaspanet/kaspad",
    "reddit": "https://www.reddit.com/r/Kaspa",
    "explorer": "https://kaspa.stream/"
  },
  "market": {
    "price": 0.03390469,
    "marketCap": 928040789,
    "marketCapRank": 73,
    "volume24h": 21881727,
    "high24h": 0.03079894,
    "low24h": 0.03032271,
    "priceChange24h": -2.36259,
    "priceChange7d": 4.27361,
    "priceChange30d": -1.8622,
    "priceChange1y": -61.2382,
    "ath": 0.207411,
    "athChangePercentage": -83.6582,
    "athDate": "2024-08-01T00:40:47.164Z",
    "atl": 0.00017105,
    "atlDate": "2022-05-26T14:42:59.316Z",
    "circulatingSupply": 27376784273.87169,
    "totalSupply": 27384862023.62956,
    "maxSupply": 28704026601,
    "fdv": 835407541
  },
  "community": {
    "twitterFollowers": null,
    "redditSubscribers": 0
  },
  "developer": {
    "githubStars": 526,
    "githubForks": 242,
    "commits4Weeks": 0
  },
  "fetchedAt": "2026-03-15T10:32:37.494Z",
  "lastMarketUpdate": "2026-04-23T19:24:33.225Z"
}