{
  "id": "lombard-protocol",
  "symbol": "bard",
  "name": "Lombard",
  "market": {
    "price": 0.487925,
    "marketCap": 109411446,
    "marketCapRank": 246,
    "volume24h": 80991509,
    "priceChange24h": -7.56313,
    "ath": 1.7,
    "athChangePercentage": -71.42262,
    "athDate": "2026-03-05T20:26:18.448Z",
    "atl": 0.32573,
    "atlDate": "2025-10-10T21:23:31.088Z",
    "circulatingSupply": 225000000,
    "totalSupply": 1000000000,
    "maxSupply": 1000000000
  },
  "lastMarketUpdate": "2026-03-22T23:47:09.009Z"
}