{
  "id": "mog-coin",
  "symbol": "mog",
  "name": "Mog Coin",
  "market": {
    "price": 1.52794e-7,
    "marketCap": 59670368,
    "marketCapRank": 428,
    "volume24h": 9612438,
    "priceChange24h": 2.83203,
    "ath": 0.00000402,
    "athChangePercentage": -96.19583,
    "athDate": "2024-12-07T03:55:46.658Z",
    "atl": 4.526e-9,
    "atlDate": "2023-07-24T17:10:57.805Z",
    "circulatingSupply": 390561998053223.3,
    "totalSupply": 390561998053223.3,
    "maxSupply": 420690000000000
  },
  "lastMarketUpdate": "2026-05-01T18:47:51.335Z"
}