{
  "id": "official-trump",
  "symbol": "trump",
  "name": "Official Trump",
  "description": "",
  "categories": [
    "Solana Ecosystem",
    "Meme",
    "Solana Meme",
    "PolitiFi",
    "Made in USA",
    "Trump-Affiliated"
  ],
  "genesisDate": null,
  "links": {
    "website": "https://gettrumpmemes.com/",
    "github": null,
    "reddit": null,
    "explorer": "https://solscan.io/token/6p6xgHyF7AeE6TZkSmFsko444wqoP15icUSqi2jfGiPN"
  },
  "market": {
    "price": 3.94,
    "marketCap": 916498145,
    "marketCapRank": 73,
    "volume24h": 439255671,
    "high24h": 4.11,
    "low24h": 3.87,
    "priceChange24h": -2.13226,
    "priceChange7d": 35.35884,
    "priceChange30d": 22.63813,
    "priceChange1y": -65.9261,
    "ath": 73.43,
    "athChangePercentage": -94.60687,
    "athDate": "2025-01-19T11:50:34.806Z",
    "atl": 2.73,
    "atlDate": "2026-03-12T14:42:04.966Z",
    "circulatingSupply": 232498807.465716,
    "totalSupply": 1000000000,
    "maxSupply": 1000000000,
    "fdv": 4051243086
  },
  "community": {
    "twitterFollowers": null,
    "redditSubscribers": 0
  },
  "developer": {
    "githubStars": 0,
    "githubForks": 0,
    "commits4Weeks": 0
  },
  "fetchedAt": "2026-03-15T10:26:59.205Z",
  "lastMarketUpdate": "2026-03-16T08:38:53.873Z"
}