{
  "id": "raydium",
  "symbol": "ray",
  "name": "Raydium",
  "market": {
    "price": 0.582144,
    "marketCap": 156379220,
    "marketCapRank": 200,
    "volume24h": 13333225,
    "priceChange24h": -2.17293,
    "ath": 16.83,
    "athChangePercentage": -96.54105,
    "athDate": "2021-09-12T20:20:23.998Z",
    "atl": 0.134391,
    "atlDate": "2022-12-29T22:15:53.927Z",
    "circulatingSupply": 268700018.217795,
    "totalSupply": 555000000,
    "maxSupply": 555000000
  },
  "lastMarketUpdate": "2026-03-23T08:10:39.110Z"
}