{
  "id": "strategic-oil-supply-2",
  "symbol": "sos",
  "name": "Strategic Oil Supply",
  "market": {
    "price": 0.00148695,
    "marketCap": 151275180,
    "marketCapRank": 206,
    "volume24h": 466459,
    "priceChange24h": -1.29472,
    "ath": 0.00976314,
    "athChangePercentage": -84.53568,
    "athDate": "2026-03-13T18:34:13.332Z",
    "atl": 0.00026894,
    "atlDate": "2026-03-16T17:20:58.014Z",
    "circulatingSupply": 100000000000,
    "totalSupply": 100000000000,
    "maxSupply": null
  },
  "lastMarketUpdate": "2026-03-19T14:14:58.674Z"
}