{
  "id": "usd-coin",
  "symbol": "usdc",
  "name": "USDC",
  "description": "USDC is a fully collateralized US dollar stablecoin. USDC is the bridge between dollars and trading on cryptocurrency exchanges. The technology behind CENTRE makes it possible to exchange value between people, businesses and financial institutions just like email between mail services and texts between SMS providers. We believe by removing artificial economic borders, we can create a more inclusive global economy.",
  "categories": [
    "Stablecoins",
    "USD Stablecoin",
    "Solana Ecosystem",
    "Avalanche Ecosystem",
    "Polygon Ecosystem",
    "Near Protocol Ecosystem",
    "Arbitrum Ecosystem",
    "Celo Ecosystem",
    "Moonriver Ecosystem",
    "Ethereum Ecosystem",
    "XDC Ecosystem",
    "Algorand Ecosystem",
    "Optimism Ecosystem",
    "Aptos Ecosystem",
    "ZkSync Ecosystem",
    "Sui Ecosystem",
    "Base Ecosystem",
    "Tron Ecosystem",
    "Starknet Ecosystem",
    "Hedera Ecosystem",
    "Stellar Ecosystem",
    "XRP Ledger Ecosystem",
    "Sonic Ecosystem",
    "Fiat-backed Stablecoin",
    "Sei Network Ecosystem",
    "World Chain Ecosystem",
    "Morph L2 Ecosystem",
    "World Liberty Financial Portfolio",
    "Ink Ecosystem",
    "Made in USA",
    "Unichain Ecosystem",
    "HyperEVM Ecosystem",
    "Plume Network Ecosystem",
    "Monad Ecosystem",
    "Base Native",
    "MiCA-Compliant Stablecoin"
  ],
  "genesisDate": null,
  "links": {
    "website": "https://www.circle.com/en/usdc",
    "github": "https://github.com/centrehq/centre-tokens",
    "reddit": null,
    "explorer": "https://etherscan.io/token/0xa0b86991c6218b36c1d19d4a2e9eb0ce3606eb48"
  },
  "market": {
    "price": 0.999722,
    "marketCap": 78667969053,
    "marketCapRank": 6,
    "volume24h": 5303553447,
    "high24h": 1,
    "low24h": 0.999815,
    "priceChange24h": -0.02295,
    "priceChange7d": -0.00818,
    "priceChange30d": 0.00018,
    "priceChange1y": 0.00084,
    "ath": 1.043,
    "athChangePercentage": -4.18067,
    "athDate": "2018-11-15T00:00:00.000Z",
    "atl": 0.877647,
    "atlDate": "2023-03-11T08:02:13.981Z",
    "circulatingSupply": 78683258624.8236,
    "totalSupply": 78688100595.68735,
    "maxSupply": null,
    "fdv": 78861563056
  },
  "community": {
    "twitterFollowers": null,
    "redditSubscribers": 0
  },
  "developer": {
    "githubStars": 735,
    "githubForks": 535,
    "commits4Weeks": 0
  },
  "fetchedAt": "2026-03-23T17:48:39.919Z",
  "lastMarketUpdate": "2026-03-25T15:39:08.420Z"
}