{
  "id": "usx",
  "symbol": "usx",
  "name": "USX",
  "market": {
    "price": 0.999846,
    "marketCap": 359602498,
    "marketCapRank": 118,
    "volume24h": 9253251,
    "priceChange24h": 0.0057,
    "ath": 1.038,
    "athChangePercentage": -3.69487,
    "athDate": "2026-01-28T23:06:53.718Z",
    "atl": 0.828472,
    "atlDate": "2025-12-26T04:30:55.143Z",
    "circulatingSupply": 359692577.862953,
    "totalSupply": 359692577.862953,
    "maxSupply": null
  },
  "lastMarketUpdate": "2026-03-21T07:05:13.760Z"
}