{
  "id": "venice-token",
  "symbol": "vvv",
  "name": "Venice Token",
  "market": {
    "price": 5.98,
    "marketCap": 267024770,
    "marketCapRank": 147,
    "volume24h": 15702455,
    "priceChange24h": 3.68404,
    "ath": 22.58,
    "athChangePercentage": -73.92194,
    "athDate": "2025-01-28T00:06:36.780Z",
    "atl": 0.91975,
    "atlDate": "2025-12-01T18:55:48.565Z",
    "circulatingSupply": 44813302.97351241,
    "totalSupply": 79077856.16502093,
    "maxSupply": null
  },
  "lastMarketUpdate": "2026-03-18T21:59:29.409Z"
}