{
  "id": "venice-token",
  "symbol": "vvv",
  "name": "Venice Token",
  "market": {
    "price": 5.8,
    "marketCap": 258266777,
    "marketCapRank": 150,
    "volume24h": 15158660,
    "priceChange24h": 4.28052,
    "ath": 22.58,
    "athChangePercentage": -74.48178,
    "athDate": "2025-01-28T00:06:36.780Z",
    "atl": 0.91975,
    "atlDate": "2025-12-01T18:55:48.565Z",
    "circulatingSupply": 44834827.17559701,
    "totalSupply": 79100453.81023374,
    "maxSupply": null
  },
  "lastMarketUpdate": "2026-03-20T07:15:07.157Z"
}