{
  "id": "wefi",
  "symbol": "wfi",
  "name": "WeFi",
  "market": {
    "price": 2.33,
    "marketCap": 189361841,
    "marketCapRank": 188,
    "volume24h": 3710383,
    "priceChange24h": -0.33276,
    "ath": 3,
    "athChangePercentage": -21.63627,
    "athDate": "2026-01-19T11:33:02.002Z",
    "atl": 0.151329,
    "atlDate": "2024-11-25T03:57:43.725Z",
    "circulatingSupply": 81461805.68597053,
    "totalSupply": 1000000000,
    "maxSupply": 1000000000
  },
  "lastMarketUpdate": "2026-03-17T14:37:55.145Z"
}