{
  "id": "zero-gravity",
  "symbol": "0g",
  "name": "0G",
  "market": {
    "price": 0.529798,
    "marketCap": 112939416,
    "marketCapRank": 248,
    "volume24h": 20557633,
    "priceChange24h": 3.12654,
    "ath": 7.05,
    "athChangePercentage": -92.47424,
    "athDate": "2025-09-23T02:51:08.602Z",
    "atl": 0.455121,
    "atlDate": "2026-02-06T00:20:58.507Z",
    "circulatingSupply": 213199722,
    "totalSupply": 1000000000,
    "maxSupply": null
  },
  "lastMarketUpdate": "2026-03-23T17:54:49.778Z"
}