{
  "id": "global-dollar",
  "name": "Global Dollar",
  "chart30d": [
    {
      "date": "2026-02-13",
      "price": 0.999818263486815
    },
    {
      "date": "2026-02-14",
      "price": 0.999728854462289
    },
    {
      "date": "2026-02-15",
      "price": 0.9998134848478397
    },
    {
      "date": "2026-02-16",
      "price": 0.9998903621362555
    },
    {
      "date": "2026-02-17",
      "price": 0.9998801065284895
    },
    {
      "date": "2026-02-18",
      "price": 0.9999421449832752
    },
    {
      "date": "2026-02-19",
      "price": 0.9997319606769791
    },
    {
      "date": "2026-02-20",
      "price": 0.9999313182941995
    },
    {
      "date": "2026-02-21",
      "price": 0.9998295540750304
    },
    {
      "date": "2026-02-22",
      "price": 1.0000292638891375
    },
    {
      "date": "2026-02-23",
      "price": 0.9999515966078852
    },
    {
      "date": "2026-02-24",
      "price": 0.9996988131080269
    },
    {
      "date": "2026-02-25",
      "price": 0.9998353782133559
    },
    {
      "date": "2026-02-26",
      "price": 0.9999614162531628
    },
    {
      "date": "2026-02-27",
      "price": 0.9999812188954725
    },
    {
      "date": "2026-02-28",
      "price": 1.000049907023586
    },
    {
      "date": "2026-03-01",
      "price": 0.9998033210161364
    },
    {
      "date": "2026-03-02",
      "price": 0.9998588161054164
    },
    {
      "date": "2026-03-03",
      "price": 0.9999476786019437
    },
    {
      "date": "2026-03-04",
      "price": 0.9999825555646857
    },
    {
      "date": "2026-03-05",
      "price": 0.999890175219758
    },
    {
      "date": "2026-03-06",
      "price": 0.9997689718127241
    },
    {
      "date": "2026-03-07",
      "price": 0.9999048022308229
    },
    {
      "date": "2026-03-08",
      "price": 1.0000604096531829
    },
    {
      "date": "2026-03-09",
      "price": 1.0000912771459365
    },
    {
      "date": "2026-03-10",
      "price": 1.0000836748689501
    },
    {
      "date": "2026-03-11",
      "price": 0.9999737138733015
    },
    {
      "date": "2026-03-12",
      "price": 0.9999525309259499
    },
    {
      "date": "2026-03-13",
      "price": 0.9999906912914347
    },
    {
      "date": "2026-03-14",
      "price": 1.000018697248513
    },
    {
      "date": "2026-03-14",
      "price": 0.99995877644029
    }
  ],
  "chart1y": [
    {
      "date": "2025-03-15",
      "price": 1.0003596613246621
    },
    {
      "date": "2025-03-16",
      "price": 1.00023588377898
    },
    {
      "date": "2025-03-17",
      "price": 0.9999793706989936
    },
    {
      "date": "2025-03-18",
      "price": 0.9998143228946531
    },
    {
      "date": "2025-03-19",
      "price": 0.999734596598162
    },
    {
      "date": "2025-03-20",
      "price": 0.9999334591644453
    },
    {
      "date": "2025-03-21",
      "price": 0.9998611091998127
    },
    {
      "date": "2025-03-22",
      "price": 0.9998976153854349
    },
    {
      "date": "2025-03-23",
      "price": 0.9999082878525409
    },
    {
      "date": "2025-03-24",
      "price": 1.0001841228189468
    },
    {
      "date": "2025-03-25",
      "price": 0.9999487136719217
    },
    {
      "date": "2025-03-26",
      "price": 1.000029247723295
    },
    {
      "date": "2025-03-27",
      "price": 1.0004450524397273
    },
    {
      "date": "2025-03-28",
      "price": 0.9998075520481904
    },
    {
      "date": "2025-03-29",
      "price": 0.999945846748559
    },
    {
      "date": "2025-03-30",
      "price": 0.9999725644575099
    },
    {
      "date": "2025-03-31",
      "price": 0.999943969334409
    },
    {
      "date": "2025-04-01",
      "price": 1.0000834636811835
    },
    {
      "date": "2025-04-02",
      "price": 1.0000263275762058
    },
    {
      "date": "2025-04-03",
      "price": 0.9997125779285108
    },
    {
      "date": "2025-04-04",
      "price": 1.0000039541290424
    },
    {
      "date": "2025-04-05",
      "price": 1.0000079850690176
    },
    {
      "date": "2025-04-06",
      "price": 0.999969827984509
    },
    {
      "date": "2025-04-07",
      "price": 1.0005755707127357
    },
    {
      "date": "2025-04-08",
      "price": 0.9996275559166276
    },
    {
      "date": "2025-04-09",
      "price": 0.9994499366937981
    },
    {
      "date": "2025-04-10",
      "price": 1.000102536686551
    },
    {
      "date": "2025-04-11",
      "price": 1.0000273134721591
    },
    {
      "date": "2025-04-12",
      "price": 0.9999724177221203
    },
    {
      "date": "2025-04-13",
      "price": 0.9998064399776706
    },
    {
      "date": "2025-04-14",
      "price": 1.0000428317040306
    },
    {
      "date": "2025-04-15",
      "price": 0.9997366287372018
    },
    {
      "date": "2025-04-16",
      "price": 0.999955545039437
    },
    {
      "date": "2025-04-17",
      "price": 0.9998855734630051
    },
    {
      "date": "2025-04-18",
      "price": 1.0001960355047772
    },
    {
      "date": "2025-04-19",
      "price": 0.9998752299146937
    },
    {
      "date": "2025-04-20",
      "price": 0.9999828746386525
    },
    {
      "date": "2025-04-21",
      "price": 1.0001662921564505
    },
    {
      "date": "2025-04-22",
      "price": 1.0002135640309444
    },
    {
      "date": "2025-04-23",
      "price": 0.9997591215182273
    },
    {
      "date": "2025-04-24",
      "price": 0.9999494348298589
    },
    {
      "date": "2025-04-25",
      "price": 0.9997650989668202
    },
    {
      "date": "2025-04-26",
      "price": 0.9998594853032147
    },
    {
      "date": "2025-04-27",
      "price": 0.999816894785144
    },
    {
      "date": "2025-04-28",
      "price": 1.0001174690415282
    },
    {
      "date": "2025-04-29",
      "price": 0.9995186948796813
    },
    {
      "date": "2025-04-30",
      "price": 1.0000759126443828
    },
    {
      "date": "2025-05-01",
      "price": 0.9997655313685366
    },
    {
      "date": "2025-05-02",
      "price": 0.9999165766624689
    },
    {
      "date": "2025-05-03",
      "price": 1.000550160933468
    },
    {
      "date": "2025-05-04",
      "price": 1.0005749214959834
    },
    {
      "date": "2025-05-05",
      "price": 0.9991097056483768
    },
    {
      "date": "2025-05-06",
      "price": 0.9998021876752723
    },
    {
      "date": "2025-05-07",
      "price": 0.9998622833280035
    },
    {
      "date": "2025-05-08",
      "price": 1.00025528434849
    },
    {
      "date": "2025-05-09",
      "price": 0.9999522160763948
    },
    {
      "date": "2025-05-10",
      "price": 0.9999294674309921
    },
    {
      "date": "2025-05-11",
      "price": 0.9999657842668532
    },
    {
      "date": "2025-05-12",
      "price": 0.9999915887594423
    },
    {
      "date": "2025-05-13",
      "price": 0.9991586232934
    },
    {
      "date": "2025-05-14",
      "price": 1.000020545989222
    },
    {
      "date": "2025-05-15",
      "price": 0.9999616021946544
    },
    {
      "date": "2025-05-16",
      "price": 0.9994237608873124
    },
    {
      "date": "2025-05-17",
      "price": 0.9997120814023283
    },
    {
      "date": "2025-05-18",
      "price": 0.9995639306379435
    },
    {
      "date": "2025-05-19",
      "price": 1.0001430528075943
    },
    {
      "date": "2025-05-20",
      "price": 1.000115487557706
    },
    {
      "date": "2025-05-21",
      "price": 1.0000257611187064
    },
    {
      "date": "2025-05-22",
      "price": 0.9997758424290948
    },
    {
      "date": "2025-05-23",
      "price": 0.9996767213751377
    },
    {
      "date": "2025-05-24",
      "price": 0.999768225801895
    },
    {
      "date": "2025-05-25",
      "price": 0.9997228817883237
    },
    {
      "date": "2025-05-26",
      "price": 0.9997031808794934
    },
    {
      "date": "2025-05-27",
      "price": 0.9997424890268036
    },
    {
      "date": "2025-05-28",
      "price": 0.9997000937125089
    },
    {
      "date": "2025-05-29",
      "price": 0.9997760442651387
    },
    {
      "date": "2025-05-30",
      "price": 0.9997365720373385
    },
    {
      "date": "2025-05-31",
      "price": 0.999870229134027
    },
    {
      "date": "2025-06-01",
      "price": 0.9999458555126096
    },
    {
      "date": "2025-06-02",
      "price": 0.999997421830524
    },
    {
      "date": "2025-06-03",
      "price": 1.00012209600993
    },
    {
      "date": "2025-06-04",
      "price": 0.9999870213910397
    },
    {
      "date": "2025-06-05",
      "price": 0.9999893178630805
    },
    {
      "date": "2025-06-06",
      "price": 0.999746574336943
    },
    {
      "date": "2025-06-07",
      "price": 0.9998227597334324
    },
    {
      "date": "2025-06-08",
      "price": 0.9996421978678581
    },
    {
      "date": "2025-06-09",
      "price": 0.9996739329278154
    },
    {
      "date": "2025-06-10",
      "price": 0.9998524771915784
    },
    {
      "date": "2025-06-11",
      "price": 0.9998653698200171
    },
    {
      "date": "2025-06-12",
      "price": 1.0000120475911873
    },
    {
      "date": "2025-06-13",
      "price": 1.0000211104880783
    },
    {
      "date": "2025-06-14",
      "price": 0.9997807894112656
    },
    {
      "date": "2025-06-15",
      "price": 0.9998214192876159
    },
    {
      "date": "2025-06-16",
      "price": 0.9995441143709599
    },
    {
      "date": "2025-06-17",
      "price": 0.9999124417853745
    },
    {
      "date": "2025-06-18",
      "price": 0.9996217672437043
    },
    {
      "date": "2025-06-19",
      "price": 0.9995927662588789
    },
    {
      "date": "2025-06-20",
      "price": 1.0001421499635332
    },
    {
      "date": "2025-06-21",
      "price": 0.9999752114922661
    },
    {
      "date": "2025-06-22",
      "price": 0.9997177982694317
    },
    {
      "date": "2025-06-23",
      "price": 0.9997508929670507
    },
    {
      "date": "2025-06-24",
      "price": 0.9999064094086068
    },
    {
      "date": "2025-06-25",
      "price": 1.000061014813183
    },
    {
      "date": "2025-06-26",
      "price": 0.9998980725187746
    },
    {
      "date": "2025-06-27",
      "price": 0.9997721863650306
    },
    {
      "date": "2025-06-28",
      "price": 0.9997376234361327
    },
    {
      "date": "2025-06-29",
      "price": 0.9998444178930703
    },
    {
      "date": "2025-06-30",
      "price": 0.9998875038270576
    },
    {
      "date": "2025-07-01",
      "price": 1.0001448216161504
    },
    {
      "date": "2025-07-02",
      "price": 1.0001609584869724
    },
    {
      "date": "2025-07-03",
      "price": 0.9998684051705644
    },
    {
      "date": "2025-07-04",
      "price": 0.9999045654832872
    },
    {
      "date": "2025-07-05",
      "price": 0.9995918229698956
    },
    {
      "date": "2025-07-06",
      "price": 0.9993406982807164
    },
    {
      "date": "2025-07-07",
      "price": 0.9993949423878026
    },
    {
      "date": "2025-07-08",
      "price": 0.9996996306404737
    },
    {
      "date": "2025-07-09",
      "price": 0.999829373105348
    },
    {
      "date": "2025-07-10",
      "price": 0.9999062760183224
    },
    {
      "date": "2025-07-11",
      "price": 0.9998715111434078
    },
    {
      "date": "2025-07-12",
      "price": 0.9998293630409348
    },
    {
      "date": "2025-07-13",
      "price": 0.9997865752490319
    },
    {
      "date": "2025-07-14",
      "price": 0.9999825699910074
    },
    {
      "date": "2025-07-15",
      "price": 0.9997964998558275
    },
    {
      "date": "2025-07-16",
      "price": 0.9997119184526361
    },
    {
      "date": "2025-07-17",
      "price": 0.9998034900324574
    },
    {
      "date": "2025-07-18",
      "price": 0.9999713064591035
    },
    {
      "date": "2025-07-19",
      "price": 0.9998718428595869
    },
    {
      "date": "2025-07-20",
      "price": 0.9998136982260346
    },
    {
      "date": "2025-07-21",
      "price": 0.9997707536973057
    },
    {
      "date": "2025-07-22",
      "price": 0.9997510775672561
    },
    {
      "date": "2025-07-23",
      "price": 0.9997088024473827
    },
    {
      "date": "2025-07-24",
      "price": 0.9997156557313525
    },
    {
      "date": "2025-07-25",
      "price": 0.9997994206197
    },
    {
      "date": "2025-07-26",
      "price": 0.9997786334324287
    },
    {
      "date": "2025-07-27",
      "price": 0.9995286987948216
    },
    {
      "date": "2025-07-28",
      "price": 0.9997064289538855
    },
    {
      "date": "2025-07-29",
      "price": 0.9995000828170985
    },
    {
      "date": "2025-07-30",
      "price": 0.9998951660854721
    },
    {
      "date": "2025-07-31",
      "price": 0.9997810874609796
    },
    {
      "date": "2025-08-01",
      "price": 0.9997275170857166
    },
    {
      "date": "2025-08-02",
      "price": 0.9996873811391902
    },
    {
      "date": "2025-08-03",
      "price": 0.9996992345399383
    },
    {
      "date": "2025-08-04",
      "price": 0.9997592781375156
    },
    {
      "date": "2025-08-05",
      "price": 0.9997018868157052
    },
    {
      "date": "2025-08-06",
      "price": 0.9998186584250552
    },
    {
      "date": "2025-08-07",
      "price": 0.9997214498179724
    },
    {
      "date": "2025-08-08",
      "price": 0.9998126310209501
    },
    {
      "date": "2025-08-09",
      "price": 0.9999353817055852
    },
    {
      "date": "2025-08-10",
      "price": 0.999831298638172
    },
    {
      "date": "2025-08-11",
      "price": 0.9999686874769472
    },
    {
      "date": "2025-08-12",
      "price": 0.9997217596493386
    },
    {
      "date": "2025-08-13",
      "price": 0.9999268606722332
    },
    {
      "date": "2025-08-14",
      "price": 0.9998989066605848
    },
    {
      "date": "2025-08-15",
      "price": 0.9997947634282974
    },
    {
      "date": "2025-08-16",
      "price": 0.9997153773469282
    },
    {
      "date": "2025-08-17",
      "price": 0.999694755035363
    },
    {
      "date": "2025-08-18",
      "price": 0.9998652394320248
    },
    {
      "date": "2025-08-19",
      "price": 0.9997967718128858
    },
    {
      "date": "2025-08-20",
      "price": 0.9996371442650421
    },
    {
      "date": "2025-08-21",
      "price": 0.9999890082034477
    },
    {
      "date": "2025-08-22",
      "price": 0.9995447829177522
    },
    {
      "date": "2025-08-23",
      "price": 0.9997149214474611
    },
    {
      "date": "2025-08-24",
      "price": 1.0003564194132728
    },
    {
      "date": "2025-08-25",
      "price": 1.0001906440012542
    },
    {
      "date": "2025-08-26",
      "price": 0.9995526959047426
    },
    {
      "date": "2025-08-27",
      "price": 0.99970650983992
    },
    {
      "date": "2025-08-28",
      "price": 0.9998016333217072
    },
    {
      "date": "2025-08-29",
      "price": 0.999838722431266
    },
    {
      "date": "2025-08-30",
      "price": 0.999956377775051
    },
    {
      "date": "2025-08-31",
      "price": 0.9998101874599389
    },
    {
      "date": "2025-09-01",
      "price": 0.9997045911577278
    },
    {
      "date": "2025-09-02",
      "price": 0.999802170942968
    },
    {
      "date": "2025-09-03",
      "price": 0.9996871570132029
    },
    {
      "date": "2025-09-04",
      "price": 0.9997871528080314
    },
    {
      "date": "2025-09-05",
      "price": 0.9993803179248749
    },
    {
      "date": "2025-09-06",
      "price": 0.9996509842598159
    },
    {
      "date": "2025-09-07",
      "price": 0.9997951195995318
    },
    {
      "date": "2025-09-08",
      "price": 0.9996746714363605
    },
    {
      "date": "2025-09-09",
      "price": 0.9998198208850313
    },
    {
      "date": "2025-09-10",
      "price": 0.9998981328855786
    },
    {
      "date": "2025-09-11",
      "price": 0.999676300699453
    },
    {
      "date": "2025-09-12",
      "price": 0.9998541613911123
    },
    {
      "date": "2025-09-13",
      "price": 0.9998531991330398
    },
    {
      "date": "2025-09-14",
      "price": 0.9998806028881981
    },
    {
      "date": "2025-09-15",
      "price": 0.9995810700870551
    },
    {
      "date": "2025-09-16",
      "price": 0.9998513068024152
    },
    {
      "date": "2025-09-17",
      "price": 0.999795542245714
    },
    {
      "date": "2025-09-18",
      "price": 0.9997027906524864
    },
    {
      "date": "2025-09-19",
      "price": 0.9998302281966481
    },
    {
      "date": "2025-09-20",
      "price": 1.0000293714799846
    },
    {
      "date": "2025-09-21",
      "price": 0.9996998526943128
    },
    {
      "date": "2025-09-22",
      "price": 0.9998402235806363
    },
    {
      "date": "2025-09-23",
      "price": 0.9997903871124078
    },
    {
      "date": "2025-09-24",
      "price": 0.9997672587593469
    },
    {
      "date": "2025-09-25",
      "price": 0.9995482396499819
    },
    {
      "date": "2025-09-26",
      "price": 0.9996897630406987
    },
    {
      "date": "2025-09-27",
      "price": 0.9997137508010768
    },
    {
      "date": "2025-09-28",
      "price": 0.9998348968270881
    },
    {
      "date": "2025-09-29",
      "price": 0.9998238459034289
    },
    {
      "date": "2025-09-30",
      "price": 0.999678498122009
    },
    {
      "date": "2025-10-01",
      "price": 0.9995390567408978
    },
    {
      "date": "2025-10-02",
      "price": 0.9998991676061875
    },
    {
      "date": "2025-10-03",
      "price": 0.9999120062264868
    },
    {
      "date": "2025-10-04",
      "price": 0.9998785978435983
    },
    {
      "date": "2025-10-05",
      "price": 0.9996547018215014
    },
    {
      "date": "2025-10-06",
      "price": 0.9995965718632194
    },
    {
      "date": "2025-10-07",
      "price": 0.9998113851554664
    },
    {
      "date": "2025-10-08",
      "price": 0.9995763622804554
    },
    {
      "date": "2025-10-09",
      "price": 0.9997256005270639
    },
    {
      "date": "2025-10-10",
      "price": 0.9998911910876236
    },
    {
      "date": "2025-10-11",
      "price": 0.9998887798693891
    },
    {
      "date": "2025-10-12",
      "price": 0.9999685375052753
    },
    {
      "date": "2025-10-13",
      "price": 0.9999820890573959
    },
    {
      "date": "2025-10-14",
      "price": 0.9999280230681397
    },
    {
      "date": "2025-10-15",
      "price": 1.0000022518374077
    },
    {
      "date": "2025-10-16",
      "price": 0.9999973259483035
    },
    {
      "date": "2025-10-17",
      "price": 0.9999890261500768
    },
    {
      "date": "2025-10-18",
      "price": 1.0000857894492556
    },
    {
      "date": "2025-10-19",
      "price": 1.000098278001158
    },
    {
      "date": "2025-10-20",
      "price": 0.9998187222489452
    },
    {
      "date": "2025-10-21",
      "price": 1.0000168751664305
    },
    {
      "date": "2025-10-22",
      "price": 0.9998413741179523
    },
    {
      "date": "2025-10-23",
      "price": 0.9999326018839365
    },
    {
      "date": "2025-10-24",
      "price": 1.0000706543194806
    },
    {
      "date": "2025-10-25",
      "price": 0.9999402834333629
    },
    {
      "date": "2025-10-26",
      "price": 0.9999162500739099
    },
    {
      "date": "2025-10-27",
      "price": 0.9999216581927254
    },
    {
      "date": "2025-10-28",
      "price": 1.0000360495320506
    },
    {
      "date": "2025-10-29",
      "price": 0.999855735996126
    },
    {
      "date": "2025-10-30",
      "price": 0.9999601611227106
    },
    {
      "date": "2025-10-31",
      "price": 0.9998721402681361
    },
    {
      "date": "2025-11-01",
      "price": 0.9997063684522548
    },
    {
      "date": "2025-11-02",
      "price": 0.9998837645738091
    },
    {
      "date": "2025-11-03",
      "price": 0.9999056665407307
    },
    {
      "date": "2025-11-04",
      "price": 0.9998499935380312
    },
    {
      "date": "2025-11-05",
      "price": 0.999819535993984
    },
    {
      "date": "2025-11-06",
      "price": 1.0000008032742345
    },
    {
      "date": "2025-11-07",
      "price": 0.9998080167825091
    },
    {
      "date": "2025-11-08",
      "price": 1.0000161235149487
    },
    {
      "date": "2025-11-09",
      "price": 0.9999820482426608
    },
    {
      "date": "2025-11-10",
      "price": 0.9997561095506896
    },
    {
      "date": "2025-11-11",
      "price": 0.9998586332487803
    },
    {
      "date": "2025-11-12",
      "price": 0.9997815503327804
    },
    {
      "date": "2025-11-13",
      "price": 0.9997511188488722
    },
    {
      "date": "2025-11-14",
      "price": 0.9996854203408216
    },
    {
      "date": "2025-11-15",
      "price": 0.9998381930687695
    },
    {
      "date": "2025-11-16",
      "price": 0.9998180571178205
    },
    {
      "date": "2025-11-17",
      "price": 0.9999034401758069
    },
    {
      "date": "2025-11-18",
      "price": 0.9997945757539592
    },
    {
      "date": "2025-11-19",
      "price": 0.9996097050981725
    },
    {
      "date": "2025-11-20",
      "price": 0.9996685384385399
    },
    {
      "date": "2025-11-21",
      "price": 0.9997016281832222
    },
    {
      "date": "2025-11-22",
      "price": 0.9997610536477864
    },
    {
      "date": "2025-11-23",
      "price": 0.9996817760069314
    },
    {
      "date": "2025-11-24",
      "price": 0.9996155426830993
    },
    {
      "date": "2025-11-25",
      "price": 0.9997511599787806
    },
    {
      "date": "2025-11-26",
      "price": 0.999650845953069
    },
    {
      "date": "2025-11-27",
      "price": 0.9997444959830388
    },
    {
      "date": "2025-11-28",
      "price": 0.9997572270948119
    },
    {
      "date": "2025-11-29",
      "price": 0.9997781068666238
    },
    {
      "date": "2025-11-30",
      "price": 0.999742527488342
    },
    {
      "date": "2025-12-01",
      "price": 0.9997657172022856
    },
    {
      "date": "2025-12-02",
      "price": 0.999752582297019
    },
    {
      "date": "2025-12-03",
      "price": 0.9998946587454568
    },
    {
      "date": "2025-12-04",
      "price": 0.999822777013927
    },
    {
      "date": "2025-12-05",
      "price": 0.9998373318473261
    },
    {
      "date": "2025-12-06",
      "price": 0.9997396606469963
    },
    {
      "date": "2025-12-07",
      "price": 0.999838229256017
    },
    {
      "date": "2025-12-08",
      "price": 0.9998000205500981
    },
    {
      "date": "2025-12-09",
      "price": 0.9996937499670773
    },
    {
      "date": "2025-12-10",
      "price": 0.9998623012096807
    },
    {
      "date": "2025-12-11",
      "price": 0.99979944805147
    },
    {
      "date": "2025-12-12",
      "price": 0.9997716313719412
    },
    {
      "date": "2025-12-13",
      "price": 0.9997740982377842
    },
    {
      "date": "2025-12-14",
      "price": 0.9998028790994519
    },
    {
      "date": "2025-12-15",
      "price": 0.9996917585221926
    },
    {
      "date": "2025-12-16",
      "price": 0.9999102820420093
    },
    {
      "date": "2025-12-17",
      "price": 0.9997363066818514
    },
    {
      "date": "2025-12-18",
      "price": 0.9997310577093105
    },
    {
      "date": "2025-12-19",
      "price": 0.9998429130106522
    },
    {
      "date": "2025-12-20",
      "price": 0.9996767682382732
    },
    {
      "date": "2025-12-21",
      "price": 0.9998945226335333
    },
    {
      "date": "2025-12-22",
      "price": 0.9998296602645478
    },
    {
      "date": "2025-12-23",
      "price": 0.9997319186930121
    },
    {
      "date": "2025-12-24",
      "price": 0.999605335522699
    },
    {
      "date": "2025-12-25",
      "price": 0.9996684871993593
    },
    {
      "date": "2025-12-26",
      "price": 0.9995733970815325
    },
    {
      "date": "2025-12-27",
      "price": 0.9996402532994836
    },
    {
      "date": "2025-12-28",
      "price": 0.9995237454150664
    },
    {
      "date": "2025-12-29",
      "price": 0.9996747202062979
    },
    {
      "date": "2025-12-30",
      "price": 0.999681778001797
    },
    {
      "date": "2025-12-31",
      "price": 0.9996982116576296
    },
    {
      "date": "2026-01-01",
      "price": 0.9995702484018893
    },
    {
      "date": "2026-01-02",
      "price": 0.9996110828178615
    },
    {
      "date": "2026-01-03",
      "price": 0.9996719026323823
    },
    {
      "date": "2026-01-04",
      "price": 0.9997056763560577
    },
    {
      "date": "2026-01-05",
      "price": 0.9995939047819857
    },
    {
      "date": "2026-01-06",
      "price": 0.999663550719033
    },
    {
      "date": "2026-01-07",
      "price": 0.9997964404520543
    },
    {
      "date": "2026-01-08",
      "price": 0.9996734817829983
    },
    {
      "date": "2026-01-09",
      "price": 0.9997734924165388
    },
    {
      "date": "2026-01-10",
      "price": 0.9995246220690657
    },
    {
      "date": "2026-01-11",
      "price": 0.9996146567513382
    },
    {
      "date": "2026-01-12",
      "price": 0.9996227174431995
    },
    {
      "date": "2026-01-13",
      "price": 0.9996605549521375
    },
    {
      "date": "2026-01-14",
      "price": 0.9996911127376827
    },
    {
      "date": "2026-01-15",
      "price": 0.9997809289850288
    },
    {
      "date": "2026-01-16",
      "price": 0.9997398244718444
    },
    {
      "date": "2026-01-17",
      "price": 0.9997721741397563
    },
    {
      "date": "2026-01-18",
      "price": 0.9997838655102128
    },
    {
      "date": "2026-01-19",
      "price": 0.999574954634926
    },
    {
      "date": "2026-01-20",
      "price": 0.9996980542060575
    },
    {
      "date": "2026-01-21",
      "price": 0.9997116601979816
    },
    {
      "date": "2026-01-22",
      "price": 0.9996985293847676
    },
    {
      "date": "2026-01-23",
      "price": 0.9997767258748268
    },
    {
      "date": "2026-01-24",
      "price": 0.9996512417581196
    },
    {
      "date": "2026-01-25",
      "price": 0.9996547584107739
    },
    {
      "date": "2026-01-26",
      "price": 0.9998219246074298
    },
    {
      "date": "2026-01-27",
      "price": 0.9996460171831336
    },
    {
      "date": "2026-01-28",
      "price": 0.9996035851812529
    },
    {
      "date": "2026-01-29",
      "price": 0.9996682810862678
    },
    {
      "date": "2026-01-30",
      "price": 0.9997618874340416
    },
    {
      "date": "2026-01-31",
      "price": 0.9997159531337052
    },
    {
      "date": "2026-02-01",
      "price": 0.9995590470660094
    },
    {
      "date": "2026-02-02",
      "price": 0.9997517879929391
    },
    {
      "date": "2026-02-03",
      "price": 0.9997102030539566
    },
    {
      "date": "2026-02-04",
      "price": 0.9996063424691543
    },
    {
      "date": "2026-02-05",
      "price": 0.9996822346270997
    },
    {
      "date": "2026-02-06",
      "price": 0.9995441336646461
    },
    {
      "date": "2026-02-07",
      "price": 0.9997933011398509
    },
    {
      "date": "2026-02-08",
      "price": 0.9997090896874119
    },
    {
      "date": "2026-02-09",
      "price": 0.9997456360851209
    },
    {
      "date": "2026-02-10",
      "price": 0.9997227803464717
    },
    {
      "date": "2026-02-11",
      "price": 0.9998663862767495
    },
    {
      "date": "2026-02-12",
      "price": 0.9997709903692229
    },
    {
      "date": "2026-02-13",
      "price": 0.999818263486815
    },
    {
      "date": "2026-02-14",
      "price": 0.999728854462289
    },
    {
      "date": "2026-02-15",
      "price": 0.9998134848478397
    },
    {
      "date": "2026-02-16",
      "price": 0.9998903621362555
    },
    {
      "date": "2026-02-17",
      "price": 0.9998801065284895
    },
    {
      "date": "2026-02-18",
      "price": 0.9999421449832752
    },
    {
      "date": "2026-02-19",
      "price": 0.9997319606769791
    },
    {
      "date": "2026-02-20",
      "price": 0.9999313182941995
    },
    {
      "date": "2026-02-21",
      "price": 0.9998295540750304
    },
    {
      "date": "2026-02-22",
      "price": 1.0000292638891375
    },
    {
      "date": "2026-02-23",
      "price": 0.9999515966078852
    },
    {
      "date": "2026-02-24",
      "price": 0.9996988131080269
    },
    {
      "date": "2026-02-25",
      "price": 0.9998353782133559
    },
    {
      "date": "2026-02-26",
      "price": 0.9999614162531628
    },
    {
      "date": "2026-02-27",
      "price": 0.9999812188954725
    },
    {
      "date": "2026-02-28",
      "price": 1.000049907023586
    },
    {
      "date": "2026-03-01",
      "price": 0.9998033210161364
    },
    {
      "date": "2026-03-02",
      "price": 0.9998588161054164
    },
    {
      "date": "2026-03-03",
      "price": 0.9999476786019437
    },
    {
      "date": "2026-03-04",
      "price": 0.9999825555646857
    },
    {
      "date": "2026-03-05",
      "price": 0.999890175219758
    },
    {
      "date": "2026-03-06",
      "price": 0.9997689718127241
    },
    {
      "date": "2026-03-07",
      "price": 0.9999048022308229
    },
    {
      "date": "2026-03-08",
      "price": 1.0000604096531829
    },
    {
      "date": "2026-03-09",
      "price": 1.0000912771459365
    },
    {
      "date": "2026-03-10",
      "price": 1.0000836748689501
    },
    {
      "date": "2026-03-11",
      "price": 0.9999737138733015
    },
    {
      "date": "2026-03-12",
      "price": 0.9999525309259499
    },
    {
      "date": "2026-03-13",
      "price": 0.9999906912914347
    },
    {
      "date": "2026-03-14",
      "price": 1.000018697248513
    },
    {
      "date": "2026-03-14",
      "price": 1.0001599376364547
    }
  ],
  "volumes30d": [
    {
      "date": "2026-02-13",
      "volume": 30136411.268645868
    },
    {
      "date": "2026-02-14",
      "volume": 28656267.81127913
    },
    {
      "date": "2026-02-15",
      "volume": 16107067.604297478
    },
    {
      "date": "2026-02-16",
      "volume": 21731812.256390482
    },
    {
      "date": "2026-02-17",
      "volume": 28960468.450129367
    },
    {
      "date": "2026-02-18",
      "volume": 18940216.06117328
    },
    {
      "date": "2026-02-19",
      "volume": 26667447.089249704
    },
    {
      "date": "2026-02-20",
      "volume": 23092798.413128626
    },
    {
      "date": "2026-02-21",
      "volume": 38475369.18787449
    },
    {
      "date": "2026-02-22",
      "volume": 9225252.81861716
    },
    {
      "date": "2026-02-23",
      "volume": 13895321.844012111
    },
    {
      "date": "2026-02-24",
      "volume": 42567486.69909393
    },
    {
      "date": "2026-02-25",
      "volume": 30811321.23721739
    },
    {
      "date": "2026-02-26",
      "volume": 39154462.06961131
    },
    {
      "date": "2026-02-27",
      "volume": 119647891.8619801
    },
    {
      "date": "2026-02-28",
      "volume": 59738680.79628879
    },
    {
      "date": "2026-03-01",
      "volume": 35625794.18390457
    },
    {
      "date": "2026-03-02",
      "volume": 34616866.5513786
    },
    {
      "date": "2026-03-03",
      "volume": 47425131.038695015
    },
    {
      "date": "2026-03-04",
      "volume": 62472977.28629403
    },
    {
      "date": "2026-03-05",
      "volume": 69021934.32282594
    },
    {
      "date": "2026-03-06",
      "volume": 62884983.80417107
    },
    {
      "date": "2026-03-07",
      "volume": 42703974.7382855
    },
    {
      "date": "2026-03-08",
      "volume": 13165771.35749302
    },
    {
      "date": "2026-03-09",
      "volume": 16595048.687597884
    },
    {
      "date": "2026-03-10",
      "volume": 44060906.25492283
    },
    {
      "date": "2026-03-11",
      "volume": 43798967.49581879
    },
    {
      "date": "2026-03-12",
      "volume": 89266508.14139625
    },
    {
      "date": "2026-03-13",
      "volume": 75493089.94836529
    },
    {
      "date": "2026-03-14",
      "volume": 47154736.453657426
    },
    {
      "date": "2026-03-14",
      "volume": 36656156.33842182
    }
  ],
  "fetchedAt": "2026-03-15T07:14:58.365Z"
}